pacoblaze/bamse_v1/iverilog/usart/usart.v
`ifndef USART_V
`define USART_V
 
module UART_TX 
   (
   input       i_Rst_H,
   input       i_Clock,
   input       i_TX_DV,
   input [7:0] i_TX_Byte,
   input [11:0] i_Clk_per_bit, 
   output reg  o_TX_Active,
   output reg  o_TX_Serial,
   output reg  o_TX_Done
   );
 
  localparam IDLE         = 3'b000;
  localparam TX_START_BIT = 3'b001;
  localparam TX_DATA_BITS = 3'b010;
  localparam TX_STOP_BIT  = 3'b011;
  localparam CLEANUP      = 3'b100;
  
  reg [2:0] r_SM_Main;
  reg [11:0] r_Clock_Count;
  reg [2:0] r_Bit_Index;
  reg [7:0] r_TX_Data;


  // Purpose: Control TX state machine
  always @(posedge i_Clock)
  begin
    if (i_Rst_H)
    begin
      r_SM_Main <= 3'b000;
      o_TX_Done <= 1'b0;
      o_TX_Active <= 1'b0;
    end
    else
    begin
      case (r_SM_Main)
      IDLE :
        begin
          o_TX_Serial   <= 1'b1;         // Drive Line High for Idle
          o_TX_Done     <= 1'b0;
          r_Clock_Count <= 0;
          r_Bit_Index   <= 0;
          
          if (i_TX_DV == 1'b1)
          begin
            o_TX_Active <= 1'b1;
            r_TX_Data   <= i_TX_Byte;
            r_SM_Main   <= TX_START_BIT;
          end
          else
            r_SM_Main <= IDLE;
        end // case: IDLE
      
      
      // Send out Start Bit. Start bit = 0
      TX_START_BIT :
        begin
          o_TX_Serial <= 1'b0;
          
          // Wait i_Clk_per_bit-1 clock cycles for start bit to finish
          if (r_Clock_Count < i_Clk_per_bit-1)
          begin
            r_Clock_Count <= r_Clock_Count + 1;
            r_SM_Main     <= TX_START_BIT;
          end
          else
          begin
            r_Clock_Count <= 0;
            r_SM_Main     <= TX_DATA_BITS;
          end
        end // case: TX_START_BIT
      
      
      // Wait i_Clk_per_bit-1 clock cycles for data bits to finish         
      TX_DATA_BITS :
        begin
          o_TX_Serial <= r_TX_Data[r_Bit_Index];
          
          if (r_Clock_Count < i_Clk_per_bit-1)
          begin
            r_Clock_Count <= r_Clock_Count + 1;
            r_SM_Main     <= TX_DATA_BITS;
          end
          else
          begin
            r_Clock_Count <= 0;
            
            // Check if we have sent out all bits
            if (r_Bit_Index < 7)
            begin
              r_Bit_Index <= r_Bit_Index + 1;
              r_SM_Main   <= TX_DATA_BITS;
            end
            else
            begin
              r_Bit_Index <= 0;
              r_SM_Main   <= TX_STOP_BIT;
            end
          end 
        end // case: TX_DATA_BITS
      
      
      // Send out Stop bit.  Stop bit = 1
      TX_STOP_BIT :
        begin
          o_TX_Serial <= 1'b1;
          
          // Wait i_Clk_per_bit-1 clock cycles for Stop bit to finish
          if (r_Clock_Count < i_Clk_per_bit-1)
          begin
            r_Clock_Count <= r_Clock_Count + 1;
            r_SM_Main     <= TX_STOP_BIT;
          end
          else
          begin
            o_TX_Done     <= 1'b1;
            r_Clock_Count <= 0;
            r_SM_Main     <= CLEANUP;
            o_TX_Active   <= 1'b0;
          end 
        end // case: TX_STOP_BIT
      
      
      // Stay here 1 clock
      CLEANUP :
        begin
          o_TX_Done <= 1'b1;
          r_SM_Main <= IDLE;
        end
      
      
      default :
        r_SM_Main <= IDLE;
      
    endcase
    end // else: !if(~i_Rst_L)
  end // always @ (posedge i_Clock or negedge i_Rst_L)

  
endmodule


module UART_RX
  (
   input            i_Rst_H,
   input            i_Clock,
   input            i_RX_Serial_asyn,
   input [11:0]		i_Clk_per_bit,
   output reg       o_RX_DV,
   output reg [7:0] o_RX_Byte
   );
   
  localparam IDLE         = 3'b000;
  localparam RX_START_BIT = 3'b001;
  localparam RX_DATA_BITS = 3'b010;
  localparam RX_STOP_BIT  = 3'b011;
  localparam CLEANUP      = 3'b100;
  
  reg [11:0] r_Clock_Count;
  reg [2:0] r_Bit_Index; //8 bits total
  reg [2:0] r_SM_Main;
    
  reg r_rx_meta;
  reg i_RX_Serial;
  
  reg [7:0] RX_Byte_temp;
  
  //Synchronize rx input
  always @(posedge i_Clock)
  begin
	r_rx_meta <= i_RX_Serial_asyn;		
	i_RX_Serial <= r_rx_meta;
  end
  
  // Purpose: Control RX state machine
  always @(posedge i_Clock)
  begin
    if (i_Rst_H)
    begin
      r_SM_Main <= 3'b000;
      o_RX_DV   <= 1'b0;
      o_RX_Byte <= 8'h00;
      RX_Byte_temp <= 8'h00;
    end
    else
    begin
      case (r_SM_Main)
      IDLE :
        begin
          o_RX_DV       <= 1'b0;
          r_Clock_Count <= 0;
          r_Bit_Index   <= 0;
          
          if (i_RX_Serial == 1'b0)          // Start bit detected
            r_SM_Main <= RX_START_BIT;
          else
            r_SM_Main <= IDLE;
        end
      
      // Check middle of start bit to make sure it's still low
      RX_START_BIT :
        begin
          if (r_Clock_Count == (i_Clk_per_bit-1)/2)
          begin
            if (i_RX_Serial == 1'b0)
            begin
              r_Clock_Count <= 0;  // reset counter, found the middle
              r_SM_Main     <= RX_DATA_BITS;
            end
            else
              r_SM_Main <= IDLE;
          end
          else
          begin
            r_Clock_Count <= r_Clock_Count + 1;
            r_SM_Main     <= RX_START_BIT;
          end
        end // case: RX_START_BIT
      
      
      // Wait i_Clk_per_bit-1 clock cycles to sample serial data
      RX_DATA_BITS :
        begin
          if (r_Clock_Count < i_Clk_per_bit-1)
          begin
            r_Clock_Count <= r_Clock_Count + 1;
            r_SM_Main     <= RX_DATA_BITS;
          end
          else
          begin
            r_Clock_Count          <= 0;
            RX_Byte_temp[r_Bit_Index] <= i_RX_Serial;
            
            // Check if we have received all bits
            if (r_Bit_Index < 7)
            begin
              r_Bit_Index <= r_Bit_Index + 1;
              r_SM_Main   <= RX_DATA_BITS;
            end
            else
            begin
              r_Bit_Index <= 0;
              r_SM_Main   <= RX_STOP_BIT;
              //o_RX_Byte <= RX_Byte_temp;
            end
          end
        end // case: RX_DATA_BITS
      
      
      // Receive Stop bit.  Stop bit = 1
      RX_STOP_BIT :
        begin
          // Wait i_Clk_per_bit-1 clock cycles for Stop bit to finish
          if (r_Clock_Count < i_Clk_per_bit-1)
          begin
            r_Clock_Count <= r_Clock_Count + 1;
            r_SM_Main     <= RX_STOP_BIT;
          end
          else
          begin
			o_RX_Byte <= RX_Byte_temp;
            o_RX_DV       <= 1'b1;
            r_Clock_Count <= 0;
            r_SM_Main     <= CLEANUP;
          end
        end // case: RX_STOP_BIT
      
      
      // Stay here 1 clock
      CLEANUP :
        begin
          r_SM_Main <= IDLE;
          o_RX_DV   <= 1'b0;
        end
      
      
      default :
        r_SM_Main <= IDLE;
      
    endcase
    end // else: !if(~i_Rst_L)
  end // always @ (posedge i_Clock or negedge i_Rst_L)
  
endmodule // UART_RX

//This module connects the USART to the BAMSE
module USART_RX_BAMSE (
	rst,
	rx,
	clk,
	clk_per_bit,
	port_out,
	//rx_ready,
	address,		
	ren,
	int_rx,
);

parameter ADDR = 8'b0000_0000; 

input rst;
input rx;
input clk;
input [11:0] clk_per_bit; // clk_per_bit = clk_frequency / bit_rate (connect to CONFIG_UART_RX1,2)
output [7:0]port_out;
//output rx_ready;
input [7:0] address;
input ren;
output int_rx;

reg int_reset;
reg int_rx;

wire rx_ready;

UART_RX rx_module(
	  .i_Rst_H(rst),
	  .i_Clock(clk),
	  .i_RX_Serial_asyn(rx),
	  .i_Clk_per_bit(clk_per_bit),
      .o_RX_DV(rx_ready),
      .o_RX_Byte(port_out)
   );

always @(posedge clk) begin
	if (rst) begin
		int_reset <= 0;			
		int_rx <= 0;
	end else begin
		if (address == ADDR) begin
			if (ren) begin 
				int_reset <= 1;
			end
		end 
		
		if (int_reset) begin
			int_rx <= 0;
			int_reset <= 0;
		end else begin
			if (rx_ready) begin
				int_rx <= 1;
			end
		end
		
	end
end

endmodule


`endif

pacoblaze/bamse_v1/iverilog/usart/usart_tb.v
//usart_tb.v
`timescale 1ns/1ps

`include "usart.v"

`define CLK_FREQ 32000000
`define BRATE 9600
`define END_SIM 36000
`define RX_UART 8'h0a


module usart_tb();

parameter N=`CLK_FREQ/`BRATE;

reg       i_Rst_H;
reg       clk;
reg       i_TX_DV;
reg [7:0] i_TX_Byte; 
reg [11:0] i_Clk_per_bit;
wire  o_TX_Active;
wire  o_TX_Serial;
wire  o_TX_Done;

reg [7:0] address;
reg ren;
wire int_rx;

wire o_Rx_DV;
wire [7:0] port_out;


UART_TX tx( 
	  .i_Rst_H(i_Rst_H),
      .i_Clock(clk),
      .i_TX_DV(i_TX_DV),
	  .i_TX_Byte(i_TX_Byte),
	  .i_Clk_per_bit(i_Clk_per_bit),
	  .o_TX_Active(o_TX_Active),
	  .o_TX_Serial(o_TX_Serial),
	  .o_TX_Done(o_TX_Done)
   );
   
   
USART_RX_BAMSE #(.ADDR(`RX_UART)) rx_mod(
	.rst(i_Rst_H),
	.rx(o_TX_Serial),
	.clk(clk),
	.clk_per_bit(i_Clk_per_bit),
	.port_out(port_out),	
	.address(address),		
	.ren(ren),
	.int_rx(int_rx)
);


parameter tck = 31.25; // clock Pailio (32 MHz)
always #(tck/2) clk = ~clk;

initial begin
	$dumpfile("dump.vcd");
	$dumpvars(0,tx,rx_mod);
	
	clk = 0;
	i_Rst_H = 0;
	i_TX_DV = 0;
	i_TX_Byte = 8'haf;
	i_Clk_per_bit = N;
	address = `RX_UART;
	ren = 0;
		
	#tck i_Rst_H = 1;
	#tck i_Rst_H = 0;
	
	#(5*tck) i_TX_DV = 1;
	#(5*tck) i_TX_DV = 0;
	
	#(35000*tck) ren = 1;
	#tck ren = 0;
	
	#(1000*tck) i_TX_Byte = 8'h53;
	#(5*tck) i_TX_DV = 1;
	#(5*tck) i_TX_DV = 0;
	
	#(`END_SIM*tck) $finish;
end


endmodule

pacoblaze/bamse_v1/iverilog/usart/dump.vcd
$date
	Wed Sep 25 23:18:01 2019
$end
$version
	Icarus Verilog
$end
$timescale
	1ps
$end
$scope module usart_tb $end
$scope module tx $end
$var wire 12 ! i_Clk_per_bit [11:0] $end
$var wire 1 " i_Clock $end
$var wire 1 # i_Rst_H $end
$var wire 8 $ i_TX_Byte [7:0] $end
$var wire 1 % i_TX_DV $end
$var reg 1 & o_TX_Active $end
$var reg 1 ' o_TX_Done $end
$var reg 1 ( o_TX_Serial $end
$var reg 3 ) r_Bit_Index [2:0] $end
$var reg 12 * r_Clock_Count [11:0] $end
$var reg 3 + r_SM_Main [2:0] $end
$var reg 8 , r_TX_Data [7:0] $end
$upscope $end
$upscope $end
$scope module usart_tb $end
$scope module rx_mod $end
$var wire 8 - address [7:0] $end
$var wire 1 " clk $end
$var wire 12 . clk_per_bit [11:0] $end
$var wire 1 / ren $end
$var wire 1 # rst $end
$var wire 1 0 rx_ready $end
$var wire 1 ( rx $end
$var wire 8 1 port_out [7:0] $end
$var reg 1 2 int_reset $end
$var reg 1 3 int_rx $end
$scope module rx_module $end
$var wire 12 4 i_Clk_per_bit [11:0] $end
$var wire 1 " i_Clock $end
$var wire 1 # i_Rst_H $end
$var wire 1 ( i_RX_Serial_asyn $end
$var reg 8 5 RX_Byte_temp [7:0] $end
$var reg 1 6 i_RX_Serial $end
$var reg 8 7 o_RX_Byte [7:0] $end
$var reg 1 0 o_RX_DV $end
$var reg 3 8 r_Bit_Index [2:0] $end
$var reg 12 9 r_Clock_Count [11:0] $end
$var reg 3 : r_SM_Main [2:0] $end
$var reg 1 ; r_rx_meta $end
$upscope $end
$upscope $end
$upscope $end
$enddefinitions $end
#0
$dumpvars
x;
bx :
bx 9
bx 8
bx 7
x6
bx 5
b110100000101 4
x3
x2
bx 1
x0
0/
b110100000101 .
b1010 -
bx ,
bx +
bx *
bx )
x(
x'
x&
0%
b10101111 $
0#
0"
b110100000101 !
$end
#15625
b0 +
b0 :
1"
#31250
0"
1#
#46875
03
02
b0 5
b0 1
b0 7
00
0&
0'
1"
#62500
0"
0#
#78125
b0 )
b0 *
1(
b0 8
b0 9
1"
#93750
0"
#109375
1;
1"
#125000
0"
#140625
16
1"
#156250
0"
#171875
1"
#187500
0"
#203125
1"
#218750
0"
1%
#234375
b1 +
b10101111 ,
1&
1"
#250000
0"
#265625
b1 *
0(
1"
#281250
0"
#296875
0;
b10 *
1"
#312500
0"
#328125
b11 *
06
1"
#343750
0"
#359375
b1 :
b100 *
1"
#375000
0"
0%
#390625
b101 *
b1 9
1"
#406250
0"
#421875
b10 9
b110 *
1"
#437500
0"
#453125
b111 *
b11 9
1"
#468750
0"
#484375
b100 9
b1000 *
1"
#500000
0"
#515625
b1001 *
b101 9
1"
#531250
0"
#546875
b110 9
b1010 *
1"
#562500
0"
#578125
b1011 *
b111 9
1"
#593750
0"
#609375
b1000 9
b1100 *
1"
#625000
0"
#640625
b1101 *
b1001 9
1"
#656250
0"
#671875
b1010 9
b1110 *
1"
#687500
0"
#703125
b1111 *
b1011 9
1"
#718750
0"
#734375
b1100 9
b10000 *
1"
#750000
0"
#765625
b10001 *
b1101 9
1"
#781250
0"
#796875
b1110 9
b10010 *
1"
#812500
0"
#828125
b10011 *
b1111 9
1"
#843750
0"
#859375
b10000 9
b10100 *
1"
#875000
0"
#890625
b10101 *
b10001 9
1"
#906250
0"
#921875
b10010 9
b10110 *
1"
#937500
0"
#953125
b10111 *
b10011 9
1"
#968750
0"
#984375
b10100 9
b11000 *
1"
#1000000
0"
#1015625
b11001 *
b10101 9
1"
#1031250
0"
#1046875
b10110 9
b11010 *
1"
#1062500
0"
#1078125
b11011 *
b10111 9
1"
#1093750
0"
#1109375
b11000 9
b11100 *
1"
#1125000
0"
#1140625
b11101 *
b11001 9
1"
#1156250
0"
#1171875
b11010 9
b11110 *
1"
#1187500
0"
#1203125
b11111 *
b11011 9
1"
#1218750
0"
#1234375
b11100 9
b100000 *
1"
#1250000
0"
#1265625
b100001 *
b11101 9
1"
#1281250
0"
#1296875
b11110 9
b100010 *
1"
#1312500
0"
#1328125
b100011 *
b11111 9
1"
#1343750
0"
#1359375
b100000 9
b100100 *
1"
#1375000
0"
#1390625
b100101 *
b100001 9
1"
#1406250
0"
#1421875
b100010 9
b100110 *
1"
#1437500
0"
#1453125
b100111 *
b100011 9
1"
#1468750
0"
#1484375
b100100 9
b101000 *
1"
#1500000
0"
#1515625
b101001 *
b100101 9
1"
#1531250
0"
#1546875
b100110 9
b101010 *
1"
#1562500
0"
#1578125
b101011 *
b100111 9
1"
#1593750
0"
#1609375
b101000 9
b101100 *
1"
#1625000
0"
#1640625
b101101 *
b101001 9
1"
#1656250
0"
#1671875
b101010 9
b101110 *
1"
#1687500
0"
#1703125
b101111 *
b101011 9
1"
#1718750
0"
#1734375
b101100 9
b110000 *
1"
#1750000
0"
#1765625
b110001 *
b101101 9
1"
#1781250
0"
#1796875
b101110 9
b110010 *
1"
#1812500
0"
#1828125
b110011 *
b101111 9
1"
#1843750
0"
#1859375
b110000 9
b110100 *
1"
#1875000
0"
#1890625
b110101 *
b110001 9
1"
#1906250
0"
#1921875
b110010 9
b110110 *
1"
#1937500
0"
#1953125
b110111 *
b110011 9
1"
#1968750
0"
#1984375
b110100 9
b111000 *
1"
#2000000
0"
#2015625
b111001 *
b110101 9
1"
#2031250
0"
#2046875
b110110 9
b111010 *
1"
#2062500
0"
#2078125
b111011 *
b110111 9
1"
#2093750
0"
#2109375
b111000 9
b111100 *
1"
#2125000
0"
#2140625
b111101 *
b111001 9
1"
#2156250
0"
#2171875
b111010 9
b111110 *
1"
#2187500
0"
#2203125
b111111 *
b111011 9
1"
#2218750
0"
#2234375
b111100 9
b1000000 *
1"
#2250000
0"
#2265625
b1000001 *
b111101 9
1"
#2281250
0"
#2296875
b111110 9
b1000010 *
1"
#2312500
0"
#2328125
b1000011 *
b111111 9
1"
#2343750
0"
#2359375
b1000000 9
b1000100 *
1"
#2375000
0"
#2390625
b1000101 *
b1000001 9
1"
#2406250
0"
#2421875
b1000010 9
b1000110 *
1"
#2437500
0"
#2453125
b1000111 *
b1000011 9
1"
#2468750
0"
#2484375
b1000100 9
b1001000 *
1"
#2500000
0"
#2515625
b1001001 *
b1000101 9
1"
#2531250
0"
#2546875
b1000110 9
b1001010 *
1"
#2562500
0"
#2578125
b1001011 *
b1000111 9
1"
#2593750
0"
#2609375
b1001000 9
b1001100 *
1"
#2625000
0"
#2640625
b1001101 *
b1001001 9
1"
#2656250
0"
#2671875
b1001010 9
b1001110 *
1"
#2687500
0"
#2703125
b1001111 *
b1001011 9
1"
#2718750
0"
#2734375
b1001100 9
b1010000 *
1"
#2750000
0"
#2765625
b1010001 *
b1001101 9
1"
#2781250
0"
#2796875
b1001110 9
b1010010 *
1"
#2812500
0"
#2828125
b1010011 *
b1001111 9
1"
#2843750
0"
#2859375
b1010000 9
b1010100 *
1"
#2875000
0"
#2890625
b1010101 *
b1010001 9
1"
#2906250
0"
#2921875
b1010010 9
b1010110 *
1"
#2937500
0"
#2953125
b1010111 *
b1010011 9
1"
#2968750
0"
#2984375
b1010100 9
b1011000 *
1"
#3000000
0"
#3015625
b1011001 *
b1010101 9
1"
#3031250
0"
#3046875
b1010110 9
b1011010 *
1"
#3062500
0"
#3078125
b1011011 *
b1010111 9
1"
#3093750
0"
#3109375
b1011000 9
b1011100 *
1"
#3125000
0"
#3140625
b1011101 *
b1011001 9
1"
#3156250
0"
#3171875
b1011010 9
b1011110 *
1"
#3187500
0"
#3203125
b1011111 *
b1011011 9
1"
#3218750
0"
#3234375
b1011100 9
b1100000 *
1"
#3250000
0"
#3265625
b1100001 *
b1011101 9
1"
#3281250
0"
#3296875
b1011110 9
b1100010 *
1"
#3312500
0"
#3328125
b1100011 *
b1011111 9
1"
#3343750
0"
#3359375
b1100000 9
b1100100 *
1"
#3375000
0"
#3390625
b1100101 *
b1100001 9
1"
#3406250
0"
#3421875
b1100010 9
b1100110 *
1"
#3437500
0"
#3453125
b1100111 *
b1100011 9
1"
#3468750
0"
#3484375
b1100100 9
b1101000 *
1"
#3500000
0"
#3515625
b1101001 *
b1100101 9
1"
#3531250
0"
#3546875
b1100110 9
b1101010 *
1"
#3562500
0"
#3578125
b1101011 *
b1100111 9
1"
#3593750
0"
#3609375
b1101000 9
b1101100 *
1"
#3625000
0"
#3640625
b1101101 *
b1101001 9
1"
#3656250
0"
#3671875
b1101010 9
b1101110 *
1"
#3687500
0"
#3703125
b1101111 *
b1101011 9
1"
#3718750
0"
#3734375
b1101100 9
b1110000 *
1"
#3750000
0"
#3765625
b1110001 *
b1101101 9
1"
#3781250
0"
#3796875
b1101110 9
b1110010 *
1"
#3812500
0"
#3828125
b1110011 *
b1101111 9
1"
#3843750
0"
#3859375
b1110000 9
b1110100 *
1"
#3875000
0"
#3890625
b1110101 *
b1110001 9
1"
#3906250
0"
#3921875
b1110010 9
b1110110 *
1"
#3937500
0"
#3953125
b1110111 *
b1110011 9
1"
#3968750
0"
#3984375
b1110100 9
b1111000 *
1"
#4000000
0"
#4015625
b1111001 *
b1110101 9
1"
#4031250
0"
#4046875
b1110110 9
b1111010 *
1"
#4062500
0"
#4078125
b1111011 *
b1110111 9
1"
#4093750
0"
#4109375
b1111000 9
b1111100 *
1"
#4125000
0"
#4140625
b1111101 *
b1111001 9
1"
#4156250
0"
#4171875
b1111010 9
b1111110 *
1"
#4187500
0"
#4203125
b1111111 *
b1111011 9
1"
#4218750
0"
#4234375
b1111100 9
b10000000 *
1"
#4250000
0"
#4265625
b10000001 *
b1111101 9
1"
#4281250
0"
#4296875
b1111110 9
b10000010 *
1"
#4312500
0"
#4328125
b10000011 *
b1111111 9
1"
#4343750
0"
#4359375
b10000000 9
b10000100 *
1"
#4375000
0"
#4390625
b10000101 *
b10000001 9
1"
#4406250
0"
#4421875
b10000010 9
b10000110 *
1"
#4437500
0"
#4453125
b10000111 *
b10000011 9
1"
#4468750
0"
#4484375
b10000100 9
b10001000 *
1"
#4500000
0"
#4515625
b10001001 *
b10000101 9
1"
#4531250
0"
#4546875
b10000110 9
b10001010 *
1"
#4562500
0"
#4578125
b10001011 *
b10000111 9
1"
#4593750
0"
#4609375
b10001000 9
b10001100 *
1"
#4625000
0"
#4640625
b10001101 *
b10001001 9
1"
#4656250
0"
#4671875
b10001010 9
b10001110 *
1"
#4687500
0"
#4703125
b10001111 *
b10001011 9
1"
#4718750
0"
#4734375
b10001100 9
b10010000 *
1"
#4750000
0"
#4765625
b10010001 *
b10001101 9
1"
#4781250
0"
#4796875
b10001110 9
b10010010 *
1"
#4812500
0"
#4828125
b10010011 *
b10001111 9
1"
#4843750
0"
#4859375
b10010000 9
b10010100 *
1"
#4875000
0"
#4890625
b10010101 *
b10010001 9
1"
#4906250
0"
#4921875
b10010010 9
b10010110 *
1"
#4937500
0"
#4953125
b10010111 *
b10010011 9
1"
#4968750
0"
#4984375
b10010100 9
b10011000 *
1"
#5000000
0"
#5015625
b10011001 *
b10010101 9
1"
#5031250
0"
#5046875
b10010110 9
b10011010 *
1"
#5062500
0"
#5078125
b10011011 *
b10010111 9
1"
#5093750
0"
#5109375
b10011000 9
b10011100 *
1"
#5125000
0"
#5140625
b10011101 *
b10011001 9
1"
#5156250
0"
#5171875
b10011010 9
b10011110 *
1"
#5187500
0"
#5203125
b10011111 *
b10011011 9
1"
#5218750
0"
#5234375
b10011100 9
b10100000 *
1"
#5250000
0"
#5265625
b10100001 *
b10011101 9
1"
#5281250
0"
#5296875
b10011110 9
b10100010 *
1"
#5312500
0"
#5328125
b10100011 *
b10011111 9
1"
#5343750
0"
#5359375
b10100000 9
b10100100 *
1"
#5375000
0"
#5390625
b10100101 *
b10100001 9
1"
#5406250
0"
#5421875
b10100010 9
b10100110 *
1"
#5437500
0"
#5453125
b10100111 *
b10100011 9
1"
#5468750
0"
#5484375
b10100100 9
b10101000 *
1"
#5500000
0"
#5515625
b10101001 *
b10100101 9
1"
#5531250
0"
#5546875
b10100110 9
b10101010 *
1"
#5562500
0"
#5578125
b10101011 *
b10100111 9
1"
#5593750
0"
#5609375
b10101000 9
b10101100 *
1"
#5625000
0"
#5640625
b10101101 *
b10101001 9
1"
#5656250
0"
#5671875
b10101010 9
b10101110 *
1"
#5687500
0"
#5703125
b10101111 *
b10101011 9
1"
#5718750
0"
#5734375
b10101100 9
b10110000 *
1"
#5750000
0"
#5765625
b10110001 *
b10101101 9
1"
#5781250
0"
#5796875
b10101110 9
b10110010 *
1"
#5812500
0"
#5828125
b10110011 *
b10101111 9
1"
#5843750
0"
#5859375
b10110000 9
b10110100 *
1"
#5875000
0"
#5890625
b10110101 *
b10110001 9
1"
#5906250
0"
#5921875
b10110010 9
b10110110 *
1"
#5937500
0"
#5953125
b10110111 *
b10110011 9
1"
#5968750
0"
#5984375
b10110100 9
b10111000 *
1"
#6000000
0"
#6015625
b10111001 *
b10110101 9
1"
#6031250
0"
#6046875
b10110110 9
b10111010 *
1"
#6062500
0"
#6078125
b10111011 *
b10110111 9
1"
#6093750
0"
#6109375
b10111000 9
b10111100 *
1"
#6125000
0"
#6140625
b10111101 *
b10111001 9
1"
#6156250
0"
#6171875
b10111010 9
b10111110 *
1"
#6187500
0"
#6203125
b10111111 *
b10111011 9
1"
#6218750
0"
#6234375
b10111100 9
b11000000 *
1"
#6250000
0"
#6265625
b11000001 *
b10111101 9
1"
#6281250
0"
#6296875
b10111110 9
b11000010 *
1"
#6312500
0"
#6328125
b11000011 *
b10111111 9
1"
#6343750
0"
#6359375
b11000000 9
b11000100 *
1"
#6375000
0"
#6390625
b11000101 *
b11000001 9
1"
#6406250
0"
#6421875
b11000010 9
b11000110 *
1"
#6437500
0"
#6453125
b11000111 *
b11000011 9
1"
#6468750
0"
#6484375
b11000100 9
b11001000 *
1"
#6500000
0"
#6515625
b11001001 *
b11000101 9
1"
#6531250
0"
#6546875
b11000110 9
b11001010 *
1"
#6562500
0"
#6578125
b11001011 *
b11000111 9
1"
#6593750
0"
#6609375
b11001000 9
b11001100 *
1"
#6625000
0"
#6640625
b11001101 *
b11001001 9
1"
#6656250
0"
#6671875
b11001010 9
b11001110 *
1"
#6687500
0"
#6703125
b11001111 *
b11001011 9
1"
#6718750
0"
#6734375
b11001100 9
b11010000 *
1"
#6750000
0"
#6765625
b11010001 *
b11001101 9
1"
#6781250
0"
#6796875
b11001110 9
b11010010 *
1"
#6812500
0"
#6828125
b11010011 *
b11001111 9
1"
#6843750
0"
#6859375
b11010000 9
b11010100 *
1"
#6875000
0"
#6890625
b11010101 *
b11010001 9
1"
#6906250
0"
#6921875
b11010010 9
b11010110 *
1"
#6937500
0"
#6953125
b11010111 *
b11010011 9
1"
#6968750
0"
#6984375
b11010100 9
b11011000 *
1"
#7000000
0"
#7015625
b11011001 *
b11010101 9
1"
#7031250
0"
#7046875
b11010110 9
b11011010 *
1"
#7062500
0"
#7078125
b11011011 *
b11010111 9
1"
#7093750
0"
#7109375
b11011000 9
b11011100 *
1"
#7125000
0"
#7140625
b11011101 *
b11011001 9
1"
#7156250
0"
#7171875
b11011010 9
b11011110 *
1"
#7187500
0"
#7203125
b11011111 *
b11011011 9
1"
#7218750
0"
#7234375
b11011100 9
b11100000 *
1"
#7250000
0"
#7265625
b11100001 *
b11011101 9
1"
#7281250
0"
#7296875
b11011110 9
b11100010 *
1"
#7312500
0"
#7328125
b11100011 *
b11011111 9
1"
#7343750
0"
#7359375
b11100000 9
b11100100 *
1"
#7375000
0"
#7390625
b11100101 *
b11100001 9
1"
#7406250
0"
#7421875
b11100010 9
b11100110 *
1"
#7437500
0"
#7453125
b11100111 *
b11100011 9
1"
#7468750
0"
#7484375
b11100100 9
b11101000 *
1"
#7500000
0"
#7515625
b11101001 *
b11100101 9
1"
#7531250
0"
#7546875
b11100110 9
b11101010 *
1"
#7562500
0"
#7578125
b11101011 *
b11100111 9
1"
#7593750
0"
#7609375
b11101000 9
b11101100 *
1"
#7625000
0"
#7640625
b11101101 *
b11101001 9
1"
#7656250
0"
#7671875
b11101010 9
b11101110 *
1"
#7687500
0"
#7703125
b11101111 *
b11101011 9
1"
#7718750
0"
#7734375
b11101100 9
b11110000 *
1"
#7750000
0"
#7765625
b11110001 *
b11101101 9
1"
#7781250
0"
#7796875
b11101110 9
b11110010 *
1"
#7812500
0"
#7828125
b11110011 *
b11101111 9
1"
#7843750
0"
#7859375
b11110000 9
b11110100 *
1"
#7875000
0"
#7890625
b11110101 *
b11110001 9
1"
#7906250
0"
#7921875
b11110010 9
b11110110 *
1"
#7937500
0"
#7953125
b11110111 *
b11110011 9
1"
#7968750
0"
#7984375
b11110100 9
b11111000 *
1"
#8000000
0"
#8015625
b11111001 *
b11110101 9
1"
#8031250
0"
#8046875
b11110110 9
b11111010 *
1"
#8062500
0"
#8078125
b11111011 *
b11110111 9
1"
#8093750
0"
#8109375
b11111000 9
b11111100 *
1"
#8125000
0"
#8140625
b11111101 *
b11111001 9
1"
#8156250
0"
#8171875
b11111010 9
b11111110 *
1"
#8187500
0"
#8203125
b11111111 *
b11111011 9
1"
#8218750
0"
#8234375
b11111100 9
b100000000 *
1"
#8250000
0"
#8265625
b100000001 *
b11111101 9
1"
#8281250
0"
#8296875
b11111110 9
b100000010 *
1"
#8312500
0"
#8328125
b100000011 *
b11111111 9
1"
#8343750
0"
#8359375
b100000000 9
b100000100 *
1"
#8375000
0"
#8390625
b100000101 *
b100000001 9
1"
#8406250
0"
#8421875
b100000010 9
b100000110 *
1"
#8437500
0"
#8453125
b100000111 *
b100000011 9
1"
#8468750
0"
#8484375
b100000100 9
b100001000 *
1"
#8500000
0"
#8515625
b100001001 *
b100000101 9
1"
#8531250
0"
#8546875
b100000110 9
b100001010 *
1"
#8562500
0"
#8578125
b100001011 *
b100000111 9
1"
#8593750
0"
#8609375
b100001000 9
b100001100 *
1"
#8625000
0"
#8640625
b100001101 *
b100001001 9
1"
#8656250
0"
#8671875
b100001010 9
b100001110 *
1"
#8687500
0"
#8703125
b100001111 *
b100001011 9
1"
#8718750
0"
#8734375
b100001100 9
b100010000 *
1"
#8750000
0"
#8765625
b100010001 *
b100001101 9
1"
#8781250
0"
#8796875
b100001110 9
b100010010 *
1"
#8812500
0"
#8828125
b100010011 *
b100001111 9
1"
#8843750
0"
#8859375
b100010000 9
b100010100 *
1"
#8875000
0"
#8890625
b100010101 *
b100010001 9
1"
#8906250
0"
#8921875
b100010010 9
b100010110 *
1"
#8937500
0"
#8953125
b100010111 *
b100010011 9
1"
#8968750
0"
#8984375
b100010100 9
b100011000 *
1"
#9000000
0"
#9015625
b100011001 *
b100010101 9
1"
#9031250
0"
#9046875
b100010110 9
b100011010 *
1"
#9062500
0"
#9078125
b100011011 *
b100010111 9
1"
#9093750
0"
#9109375
b100011000 9
b100011100 *
1"
#9125000
0"
#9140625
b100011101 *
b100011001 9
1"
#9156250
0"
#9171875
b100011010 9
b100011110 *
1"
#9187500
0"
#9203125
b100011111 *
b100011011 9
1"
#9218750
0"
#9234375
b100011100 9
b100100000 *
1"
#9250000
0"
#9265625
b100100001 *
b100011101 9
1"
#9281250
0"
#9296875
b100011110 9
b100100010 *
1"
#9312500
0"
#9328125
b100100011 *
b100011111 9
1"
#9343750
0"
#9359375
b100100000 9
b100100100 *
1"
#9375000
0"
#9390625
b100100101 *
b100100001 9
1"
#9406250
0"
#9421875
b100100010 9
b100100110 *
1"
#9437500
0"
#9453125
b100100111 *
b100100011 9
1"
#9468750
0"
#9484375
b100100100 9
b100101000 *
1"
#9500000
0"
#9515625
b100101001 *
b100100101 9
1"
#9531250
0"
#9546875
b100100110 9
b100101010 *
1"
#9562500
0"
#9578125
b100101011 *
b100100111 9
1"
#9593750
0"
#9609375
b100101000 9
b100101100 *
1"
#9625000
0"
#9640625
b100101101 *
b100101001 9
1"
#9656250
0"
#9671875
b100101010 9
b100101110 *
1"
#9687500
0"
#9703125
b100101111 *
b100101011 9
1"
#9718750
0"
#9734375
b100101100 9
b100110000 *
1"
#9750000
0"
