pacoblaze/bamse_v1/iverilog/timer/timer.v
`ifndef TIMER_V
`define TIMER_V

module timer(
	clk_in,
	rst,
	prescaler_conf,
	timer_conf,
	en,
	go,
	auto_load,
	tmr_int_clear,	
	tmr_int,
	go_clear	
);

input clk_in;
input rst; //(H)
input [2:0] prescaler_conf; //Select between 8 possible frequencies 000 -> clk_in : 111 -> clk_in/128
input [15:0] timer_conf; // 16 bit load value for the counter 
input en; //enable (H)
input go; //start (H)
input auto_load; //automatic restart timer after rolloff (H)
input tmr_int_clear; 
output reg tmr_int; //interrupt (H)
output reg go_clear;

reg [6:0] prescaler_out;

//Prescaler
reg prescaler_reset;

always @(posedge clk_in) begin
	if (rst) begin
		prescaler_out <= 0;		
	end else begin
		if (en) begin
			if (prescaler_reset) begin
				prescaler_out <= 0;
			end else begin
				prescaler_out <= prescaler_out + 1;
			end		
		end
	end
end

//Prescaler selector

reg selected_freq;

always @(*) begin
	case (prescaler_conf)
		3'b000: selected_freq = clk_in;
		3'b001: selected_freq = prescaler_out[0];
		3'b010: selected_freq = prescaler_out[1];
		3'b011: selected_freq = prescaler_out[2];
		3'b100: selected_freq = prescaler_out[3];
		3'b101: selected_freq = prescaler_out[4]; 
		3'b110: selected_freq = prescaler_out[5];
		3'b111: selected_freq = prescaler_out[6];
	endcase
end

//Timer
reg [15:0] timer_count;
reg [1:0] timer_state;

parameter IDLE  = 2'b00, 
		  GO =    2'b01,
		  ROLL  = 2'b11;
		 
always @(posedge selected_freq) begin
	if (rst) begin
		timer_count <= 0;					
		tmr_int <= 0;
		timer_state <= IDLE;
		prescaler_reset <= 0;
		go_clear <= 0;
	end else begin 
		if (en) begin
			case (timer_state)
				IDLE:	begin
							if (go) begin 
								timer_count <= timer_conf;														
								timer_state <= GO;
								prescaler_reset <= 1;
							end 
							
							if (tmr_int_clear) tmr_int <= 0;
						
						end
				GO:		begin 
							prescaler_reset <= 0;
							timer_count <= timer_count + 1;
							
							if (timer_count == 16'hffff) begin
								timer_state <= ROLL;
								go_clear <= 1;
							end							
							
							if (tmr_int_clear) tmr_int <= 0;													
						end
				ROLL: 	begin
							tmr_int <= 1;
							go_clear <= 0;
							if (auto_load) begin
								timer_count <= timer_conf;														
								timer_state <= GO;
							end else begin
								timer_state <= IDLE;
							end
						end				
			endcase
		end else begin
			timer_state <= IDLE;
		end
	
	end
end

endmodule

/**************************/
/*    TIMER BAMSE         */
/**************************/

// Configuration word
//      B7       B6        B5       B4        B3        B2        B1        B0
//   	-        PS2      PS1       PS0      AUTO_LD    EN        GO      INT_TMR

module TIMER_BAMSE (
	input clk,
	input rst, //(H)
	input [15:0] timer_conf, // 16 bit load value for the counter 
	//input en, //enable (H)
	output tmr_interrupt, //interrupt (H)
	input [7:0] address,
	input [7:0] config_in,
	output [7:0] config_out,
	input ren,
	input wen	
);

parameter ADDR = 8'h00; // This same register address is used for read and write

reg  [7:0] timer_config_reg;
wire [1:0] mask_reset;
reg tmr_int_clear;
wire go_clear;
wire tmr_int;

assign mask_reset[0] = tmr_int;
assign mask_reset[1] = go_clear;

always @(posedge clk) begin
	if (rst) begin
		timer_config_reg <= 0;
		tmr_int_clear <= 0;
	end else if (|mask_reset) begin // Signals from timer module 
			if (mask_reset[0]) timer_config_reg[0] <= 1; // To interrupt out
			if (mask_reset[1]) timer_config_reg[1] <= 0; // To GO
		end	else if (address == ADDR) begin //signals written from software
		if (wen) begin
			timer_config_reg <= config_in;
			if (config_in[0] == 0) tmr_int_clear <= 1;			
		end		
		if (tmr_int_clear) tmr_int_clear <= 0;
	end
end

assign config_out = timer_config_reg;

wire go, en, auto_load;
wire [2:0] prescaler_conf;

assign tmr_interrupt = config_out[0];
assign go = config_out[1];
assign en = config_out[2];
assign auto_load = config_out[3];
assign prescaler_conf[2:0] = config_out[6:4];

timer tmt(
	.clk_in(clk),
	.rst(rst),
	.prescaler_conf(prescaler_conf),
	.timer_conf(timer_conf),
	.en(en),
	.go(go),
	.auto_load(auto_load),
	.tmr_int_clear(tmr_int_clear),	
	.tmr_int(tmr_int),
	.go_clear(go_clear)
);


endmodule

`endif

pacoblaze/bamse_v1/iverilog/timer/timer_tb.v
//timer_tb.v

`timescale 1ns/1ps

`include "timer.v"

module timer_tb();

reg clk;
reg rst;
reg [2:0] prescaler_conf;
reg [15:0] timer_conf; 
reg en; //enable (H)
reg go; //start (H)
reg auto_load; //automatic restart timer after rolloff (H)
wire tmr_interrupt; //interrupt (H)
reg [7:0] address;
wire [7:0] config_in;
wire [7:0] config_out;
reg ren;
reg wen;

assign config_in = {{1'b0},prescaler_conf,auto_load,en,go,tmr_interrupt};
parameter ADDR=8'h00;
/*
//Resetable register
always @(posedge clk_in) begin
	if (rst) begin
		go_aux <= 0;
	end else if (go_clear) begin
		go_aux <= ~go_clear & go_aux;
	end	else if (address == (ADDR && wen)) begin
		go_aux <= go;	
	end
end
*/

TIMER_BAMSE #(.ADDR(8'h00)) dut(
	.clk(clk),
	.rst(rst),	
	.timer_conf(timer_conf),
	//.en(en),		
	.tmr_interrupt(tmr_interrupt),
	.address(address),
	.config_in(config_in),
	.config_out(config_out),
	.ren(ren),
	.wen(wen)
);

always #(2) clk = ~clk;

initial begin
	$dumpfile("dump.vcd");
	$dumpvars(0,dut,config_in,config_out);
	
	clk = 0;
	rst = 0;
	prescaler_conf = 0;
	timer_conf = 16'hfff0;
	en = 0;
	go = 0;
	auto_load = 0;
	address = 8'h00;
	ren = 0;
	wen = 0;
		
	
	#10 rst = 1;
	#10 rst = 0;
	
	#50 en = 1;
	#10 go = 1;
	#10 wen = 1;
	#10 go = 0; wen = 0;
	
	
		/*
	#100 rst = 1;
	#10 rst = 0;
	#10 auto_load = 1;
	#10 go = 1;
	#10 go = 0;	
	
	#100 ren = 1;
	#10 ren = 0;
	
	#100 ren = 1;
	#10 ren = 0;
	
	#200 */
	#(250) $finish;
end

endmodule

pacoblaze/bamse_v1/iverilog/timer/dump.vcd
$date
	Thu Oct  3 15:18:45 2019
$end
$version
	Icarus Verilog
$end
$timescale
	1ps
$end
$scope module timer_tb $end
$scope module dut $end
$var wire 8 ! address [7:0] $end
$var wire 1 " clk $end
$var wire 8 # config_in [7:0] $end
$var wire 1 $ ren $end
$var wire 1 % rst $end
$var wire 16 & timer_conf [15:0] $end
$var wire 1 ' wen $end
$var wire 1 ( tmr_interrupt $end
$var wire 1 ) tmr_int $end
$var wire 3 * prescaler_conf [2:0] $end
$var wire 2 + mask_reset [1:0] $end
$var wire 1 , go_clear $end
$var wire 1 - go $end
$var wire 1 . en $end
$var wire 8 / config_out [7:0] $end
$var wire 1 0 auto_load $end
$var reg 8 1 timer_config_reg [7:0] $end
$var reg 1 2 tmr_int_clear $end
$scope module tmt $end
$var wire 1 0 auto_load $end
$var wire 1 " clk_in $end
$var wire 1 . en $end
$var wire 1 - go $end
$var wire 3 3 prescaler_conf [2:0] $end
$var wire 1 % rst $end
$var wire 16 4 timer_conf [15:0] $end
$var wire 1 2 tmr_int_clear $end
$var reg 1 , go_clear $end
$var reg 7 5 prescaler_out [6:0] $end
$var reg 1 6 prescaler_reset $end
$var reg 1 7 selected_freq $end
$var reg 16 8 timer_count [15:0] $end
$var reg 2 9 timer_state [1:0] $end
$var reg 1 ) tmr_int $end
$upscope $end
$upscope $end
$upscope $end
$scope module timer_tb $end
$var wire 8 : config_in [7:0] $end
$upscope $end
$scope module timer_tb $end
$var wire 8 ; config_out [7:0] $end
$upscope $end
$enddefinitions $end
#0
$dumpvars
bx ;
b0x :
bx 9
bx 8
x7
x6
bx 5
b1111111111110000 4
bx 3
x2
bx 1
x0
bx /
x.
x-
x,
bx +
bx *
x)
x(
0'
b1111111111110000 &
0%
0$
b0x #
0"
b0 !
$end
#2000
1"
#4000
0"
#6000
1"
#8000
0"
#10000
0,
06
b0 9
b0 +
0)
b0 8
17
b0 #
b0 :
0(
0-
0.
00
b0 *
b0 3
b0 5
02
b0 /
b0 1
b0 ;
1"
1%
#12000
07
0"
#14000
17
1"
#16000
07
0"
#18000
17
1"
#20000
07
0"
0%
#22000
17
1"
#24000
07
0"
#26000
17
1"
#28000
07
0"
#30000
17
1"
#32000
07
0"
#34000
17
1"
#36000
07
0"
#38000
17
1"
#40000
07
0"
#42000
17
1"
#44000
07
0"
#46000
17
1"
#48000
07
0"
#50000
17
1"
#52000
07
0"
#54000
17
1"
#56000
07
0"
#58000
17
1"
#60000
07
0"
#62000
17
1"
#64000
07
0"
#66000
17
1"
#68000
07
0"
#70000
17
1"
b100 #
b100 :
#72000
07
0"
#74000
17
1"
#76000
07
0"
#78000
17
1"
#80000
07
0"
b110 #
b110 :
#82000
17
1"
#84000
07
0"
#86000
17
1"
#88000
07
0"
#90000
1-
1.
12
b110 /
b110 1
b110 ;
17
1"
1'
#92000
07
0"
#94000
16
b1 9
b1111111111110000 8
02
b1 5
17
1"
#96000
07
0"
#98000
b1111111111110001 8
06
b0 5
12
17
1"
#100000
07
0"
0'
b100 #
b100 :
#102000
b1111111111110010 8
02
b1 5
17
1"
#104000
07
0"
#106000
b1111111111110011 8
b10 5
17
1"
#108000
07
0"
#110000
b1111111111110100 8
b11 5
17
1"
#112000
07
0"
#114000
b1111111111110101 8
b100 5
17
1"
#116000
07
0"
#118000
b1111111111110110 8
b101 5
17
1"
#120000
07
0"
#122000
b1111111111110111 8
b110 5
17
1"
#124000
07
0"
#126000
b1111111111111000 8
b111 5
17
1"
#128000
07
0"
#130000
b1111111111111001 8
b1000 5
17
1"
#132000
07
0"
#134000
b1111111111111010 8
b1001 5
17
1"
#136000
07
0"
#138000
b1111111111111011 8
b1010 5
17
1"
#140000
07
0"
#142000
b1111111111111100 8
b1011 5
17
1"
#144000
07
0"
#146000
b1111111111111101 8
b1100 5
17
1"
#148000
07
0"
#150000
b1111111111111110 8
b1101 5
17
1"
#152000
07
0"
#154000
b1111111111111111 8
b1110 5
17
1"
#156000
07
0"
#158000
b10 +
1,
b11 9
b0 8
b1111 5
17
1"
#160000
07
0"
#162000
0-
b0 9
0,
b1 +
1)
b10000 5
b100 /
b100 1
b100 ;
17
1"
#164000
07
0"
#166000
b101 #
b101 :
1(
b101 /
b101 1
b101 ;
b10001 5
17
1"
#168000
07
0"
#170000
b10010 5
17
1"
#172000
07
0"
#174000
b10011 5
17
1"
#176000
07
0"
#178000
b10100 5
17
1"
#180000
07
0"
#182000
b10101 5
17
1"
#184000
07
0"
#186000
b10110 5
17
1"
#188000
07
0"
#190000
b10111 5
17
1"
#192000
07
0"
#194000
b11000 5
17
1"
#196000
07
0"
#198000
b11001 5
17
1"
#200000
07
0"
#202000
b11010 5
17
1"
#204000
07
0"
#206000
b11011 5
17
1"
#208000
07
0"
#210000
b11100 5
17
1"
#212000
07
0"
#214000
b11101 5
17
1"
#216000
07
0"
#218000
b11110 5
17
1"
#220000
07
0"
#222000
b11111 5
17
1"
#224000
07
0"
#226000
b100000 5
17
1"
#228000
07
0"
#230000
b100001 5
17
1"
#232000
07
0"
#234000
b100010 5
17
1"
#236000
07
0"
#238000
b100011 5
17
1"
#240000
07
0"
#242000
b100100 5
17
1"
#244000
07
0"
#246000
b100101 5
17
1"
#248000
07
0"
#250000
b100110 5
17
1"
#252000
07
0"
#254000
b100111 5
17
1"
#256000
07
0"
#258000
b101000 5
17
1"
#260000
07
0"
#262000
b101001 5
17
1"
#264000
07
0"
#266000
b101010 5
17
1"
#268000
07
0"
#270000
b101011 5
17
1"
#272000
07
0"
#274000
b101100 5
17
1"
#276000
07
0"
#278000
b101101 5
17
1"
#280000
07
0"
#282000
b101110 5
17
1"
#284000
07
0"
#286000
b101111 5
17
1"
#288000
07
0"
#290000
b110000 5
17
1"
#292000
07
0"
#294000
b110001 5
17
1"
#296000
07
0"
#298000
b110010 5
17
1"
#300000
07
0"
#302000
b110011 5
17
1"
#304000
07
0"
#306000
b110100 5
17
1"
#308000
07
0"
#310000
b110101 5
17
1"
#312000
07
0"
#314000
b110110 5
17
1"
#316000
07
0"
#318000
b110111 5
17
1"
#320000
07
0"
#322000
b111000 5
17
1"
#324000
07
0"
#326000
b111001 5
17
1"
#328000
07
0"
#330000
b111010 5
17
1"
#332000
07
0"
#334000
b111011 5
17
1"
#336000
07
0"
#338000
b111100 5
17
1"
#340000
07
0"
#342000
b111101 5
17
1"
#344000
07
0"
#346000
b111110 5
17
1"
#348000
07
0"
#350000
b111111 5
17
1"
