pacoblaze/bamse_v1/iverilog/timer/timer.v
`ifndef TIMER_V
`define TIMER_V

module timer(
	input clk_in,
	input rst, //(H)
	input [2:0] prescaler_conf, //Select between 8 possible frequencies 000 -> clk_in : 111 -> clk_in/128
	input [15:0] timer_conf, // 16 bit load value for the counter 
	input en, //enable (H)
	input go, //start (H)
	input auto_load, //automatic restart timer after rolloff (H)
	output reg tmr_int, //roll of - interrupt 1 pulse (H)
	output reg go_clear // 1 pulse (H)
);

reg [6:0] prescaler_out;

//Prescaler
reg prescaler_reset;

always @(posedge clk_in) begin
	if (rst) begin
		prescaler_out <= 0;		
	end else begin
		if (en) begin
			if (prescaler_reset) begin
				prescaler_out <= 0;
			end else begin
				prescaler_out <= prescaler_out + 1;
			end		
		end
	end
end

//Prescaler selector
reg selected_freq;

always @(*) begin
	case (prescaler_conf)
		3'b000: selected_freq = clk_in;
		3'b001: selected_freq = prescaler_out[0];
		3'b010: selected_freq = prescaler_out[1];
		3'b011: selected_freq = prescaler_out[2];
		3'b100: selected_freq = prescaler_out[3];
		3'b101: selected_freq = prescaler_out[4]; 
		3'b110: selected_freq = prescaler_out[5];
		3'b111: selected_freq = prescaler_out[6];
	endcase
end

//Timer
reg [15:0] timer_count;
reg [1:0] timer_state;

parameter IDLE  = 2'b00, 
		  GO =    2'b01,
		  ROLL  = 2'b11;
		 
always @(posedge selected_freq) begin
	if (rst) begin
		timer_count <= 0;					
		tmr_int <= 0;
		timer_state <= IDLE;
		prescaler_reset <= 0;
		go_clear <= 0;
	end else begin 
		if (en) begin
			case (timer_state)
				IDLE:	begin
							if (go) begin 
								timer_count <= timer_conf;														
								timer_state <= GO;
								prescaler_reset <= 1;
							end 
														
							tmr_int <= 0;
						
						end
				GO:		begin 
							prescaler_reset <= 0;
							timer_count <= timer_count + 1;
							
							if (timer_count == 16'hffff) begin
								timer_state <= ROLL;
								go_clear <= 1;
							end							
							
							tmr_int <= 0;													
						end
				ROLL: 	begin
							tmr_int <= 1;
							go_clear <= 0;
							if (auto_load) begin
								timer_count <= timer_conf;														
								timer_state <= GO;
							end else begin
								timer_state <= IDLE;
							end
						end				
			endcase
		end else begin
			timer_state <= IDLE;
		end
	
	end
end

endmodule

/**************************/
/*    TIMER BAMSE         */
/**************************/

// Configuration word (config_in and config_out)
//      B7       B6        B5       B4        B3        B2        B1        B0
//   	-        PS2      PS1       PS0      AUTO_LD    EN        GO      INT_TMR
//
// Note: GO and INT_TMR R&W bits that are set/cleared by the timer.
// 

module TIMER_BAMSE (
	input clk,
	input rst, //(H)
	input [15:0] timer_conf, // 16 bit load value for the counter 
	input [7:0] address,
	input [7:0] config_in,
	output [7:0] config_out,
	input ren,
	input wen	
);

parameter ADDR = 8'h00; // This same register address is used for read and write

reg  [7:0] timer_config_reg;
wire [1:0] mask_reset;
wire go_clear;
wire tmr_int;

//outputs from timer
assign mask_reset[0] = tmr_int;
assign mask_reset[1] = go_clear;

always @(posedge clk) begin
	if (rst) begin
		timer_config_reg <= 0;
	end else if (|mask_reset) begin // Signals from timer module 
			if (mask_reset[0]) timer_config_reg[0] <= 1; // To interrupt out
			if (mask_reset[1]) timer_config_reg[1] <= 0; // To GO
		end	else if (address == ADDR) begin //signals written from software
		if (wen) begin
			timer_config_reg <= config_in;
		end				
	end
end

assign config_out = timer_config_reg;

wire go, en, auto_load;
wire [2:0] prescaler_conf;

assign go = config_out[1];
assign en = config_out[2];
assign auto_load = config_out[3];
assign prescaler_conf[2:0] = config_out[6:4];

timer tmt(
	.clk_in(clk),
	.rst(rst),
	.prescaler_conf(prescaler_conf),
	.timer_conf(timer_conf),
	.en(en),
	.go(go),
	.auto_load(auto_load),	
	.tmr_int(tmr_int),
	.go_clear(go_clear)
);

endmodule

`endif

pacoblaze/bamse_v1/iverilog/timer/timer_tb.v
//timer_tb.v

`timescale 1ns/1ps

`include "timer.v"

module timer_tb();

reg clk;
reg rst;
reg [2:0] prescaler_conf;
reg [15:0] timer_conf; 
reg en; //enable (H)
reg go; //start (H)
reg auto_load; //automatic restart timer after rolloff (H)
reg int;
reg [7:0] address;
wire [7:0] config_in;
wire [7:0] config_out;
reg ren;
reg wen;

wire interrupt;

assign interrupt = config_out[0];

assign config_in = {{1'b0},prescaler_conf,auto_load,en,go,int};
parameter ADDR=8'h00;

TIMER_BAMSE #(.ADDR(8'h00)) dut(
	.clk(clk),
	.rst(rst),	
	.timer_conf(timer_conf),
	.address(address),
	.config_in(config_in),
	.config_out(config_out),
	.ren(ren),
	.wen(wen)
);

always #(2) clk = ~clk;

initial begin
	$dumpfile("dump.vcd");
	$dumpvars(-1,dut,config_in,config_out,interrupt);
	
	en = 0;
	clk = 0;
	rst = 0;
	prescaler_conf = 0;
	timer_conf = 16'hfff0;
	en = 0;
	go = 0;
	auto_load = 0;
	address = 8'h00;
	ren = 0;
	wen = 0;
	int = 0;
		
	
	#10 rst = 1;
	#10 rst = 0;
	
	#50 en = 1;
	#10 go = 1;
	#10 wen = 1;
	#10 go = 0; wen = 0;
	
	#80 wen = 1; 
	#10 wen = 0;
	
	#50 auto_load = 1; go = 1;
	#10 wen = 1;
	#10 wen = 0;
	
	#70 go = 0; int = 0;
	#10 wen = 1;
	#10 wen = 0;
	
	#80 auto_load = 0; int = 0;
	#10 wen = 1;
	#10 wen = 0;
	
	#80 auto_load = 1;
	#10 wen = 1;
	#10 wen = 0;
	
	#80 en = 0;
	#10 wen = 1;
	#10 wen = 0;
	
	
	 
	
	#(100) $finish;
end

endmodule

pacoblaze/bamse_v1/iverilog/timer/dump.vcd
$date
	Thu Oct  3 23:24:34 2019
$end
$version
	Icarus Verilog
$end
$timescale
	1ps
$end
$scope module timer_tb $end
$scope module dut $end
$var wire 8 ! address [7:0] $end
$var wire 1 " clk $end
$var wire 8 # config_in [7:0] $end
$var wire 1 $ ren $end
$var wire 1 % rst $end
$var wire 16 & timer_conf [15:0] $end
$var wire 1 ' wen $end
$var wire 1 ( tmr_int $end
$var wire 3 ) prescaler_conf [2:0] $end
$var wire 2 * mask_reset [1:0] $end
$var wire 1 + go_clear $end
$var wire 1 , go $end
$var wire 1 - en $end
$var wire 8 . config_out [7:0] $end
$var wire 1 / auto_load $end
$var reg 8 0 timer_config_reg [7:0] $end
$scope module tmt $end
$var wire 1 / auto_load $end
$var wire 1 " clk_in $end
$var wire 1 - en $end
$var wire 1 , go $end
$var wire 3 1 prescaler_conf [2:0] $end
$var wire 1 % rst $end
$var wire 16 2 timer_conf [15:0] $end
$var reg 1 + go_clear $end
$var reg 7 3 prescaler_out [6:0] $end
$var reg 1 4 prescaler_reset $end
$var reg 1 5 selected_freq $end
$var reg 16 6 timer_count [15:0] $end
$var reg 2 7 timer_state [1:0] $end
$var reg 1 ( tmr_int $end
$upscope $end
$upscope $end
$upscope $end
$scope module timer_tb $end
$var wire 8 8 config_in [7:0] $end
$upscope $end
$scope module timer_tb $end
$var wire 8 9 config_out [7:0] $end
$upscope $end
$scope module timer_tb $end
$var wire 1 : interrupt $end
$upscope $end
$enddefinitions $end
#0
$dumpvars
x:
bx 9
b0 8
bx 7
bx 6
x5
x4
bx 3
b1111111111110000 2
bx 1
bx 0
x/
bx .
x-
x,
x+
bx *
bx )
x(
0'
b1111111111110000 &
0%
0$
b0 #
0"
b0 !
$end
#2000
1"
#4000
0"
#6000
1"
#8000
0"
#10000
0+
04
b0 7
b0 *
0(
b0 6
15
0,
0-
0/
b0 )
b0 1
0:
b0 3
b0 .
b0 0
b0 9
1"
1%
#12000
05
0"
#14000
15
1"
#16000
05
0"
#18000
15
1"
#20000
05
0"
0%
#22000
15
1"
#24000
05
0"
#26000
15
1"
#28000
05
0"
#30000
15
1"
#32000
05
0"
#34000
15
1"
#36000
05
0"
#38000
15
1"
#40000
05
0"
#42000
15
1"
#44000
05
0"
#46000
15
1"
#48000
05
0"
#50000
15
1"
#52000
05
0"
#54000
15
1"
#56000
05
0"
#58000
15
1"
#60000
05
0"
#62000
15
1"
#64000
05
0"
#66000
15
1"
#68000
05
0"
#70000
15
1"
b100 #
b100 8
#72000
05
0"
#74000
15
1"
#76000
05
0"
#78000
15
1"
#80000
05
0"
b110 #
b110 8
#82000
15
1"
#84000
05
0"
#86000
15
1"
#88000
05
0"
#90000
1,
1-
b110 .
b110 0
b110 9
15
1"
1'
#92000
05
0"
#94000
14
b1 7
b1111111111110000 6
b1 3
15
1"
#96000
05
0"
#98000
b1111111111110001 6
04
b0 3
15
1"
#100000
05
0"
0'
b100 #
b100 8
#102000
b1111111111110010 6
b1 3
15
1"
#104000
05
0"
#106000
b1111111111110011 6
b10 3
15
1"
#108000
05
0"
#110000
b1111111111110100 6
b11 3
15
1"
#112000
05
0"
#114000
b1111111111110101 6
b100 3
15
1"
#116000
05
0"
#118000
b1111111111110110 6
b101 3
15
1"
#120000
05
0"
#122000
b1111111111110111 6
b110 3
15
1"
#124000
05
0"
#126000
b1111111111111000 6
b111 3
15
1"
#128000
05
0"
#130000
b1111111111111001 6
b1000 3
15
1"
#132000
05
0"
#134000
b1111111111111010 6
b1001 3
15
1"
#136000
05
0"
#138000
b1111111111111011 6
b1010 3
15
1"
#140000
05
0"
#142000
b1111111111111100 6
b1011 3
15
1"
#144000
05
0"
#146000
b1111111111111101 6
b1100 3
15
1"
#148000
05
0"
#150000
b1111111111111110 6
b1101 3
15
1"
#152000
05
0"
#154000
b1111111111111111 6
b1110 3
15
1"
#156000
05
0"
#158000
b10 *
1+
b11 7
b0 6
b1111 3
15
1"
#160000
05
0"
#162000
0,
b0 7
0+
b1 *
1(
b10000 3
b100 .
b100 0
b100 9
15
1"
#164000
05
0"
#166000
1:
b0 *
0(
b101 .
b101 0
b101 9
b10001 3
15
1"
#168000
05
0"
#170000
b10010 3
15
1"
#172000
05
0"
#174000
b10011 3
15
1"
#176000
05
0"
#178000
b10100 3
15
1"
#180000
05
0"
1'
#182000
0:
b100 .
b100 0
b100 9
b10101 3
15
1"
#184000
05
0"
#186000
b10110 3
15
1"
#188000
05
0"
#190000
b10111 3
15
1"
0'
#192000
05
0"
#194000
b11000 3
15
1"
#196000
05
0"
#198000
b11001 3
15
1"
#200000
05
0"
#202000
b11010 3
15
1"
#204000
05
0"
#206000
b11011 3
15
1"
#208000
05
0"
#210000
b11100 3
15
1"
#212000
05
0"
#214000
b11101 3
15
1"
#216000
05
0"
#218000
b11110 3
15
1"
#220000
05
0"
#222000
b11111 3
15
1"
#224000
05
0"
#226000
b100000 3
15
1"
#228000
05
0"
#230000
b100001 3
15
1"
#232000
05
0"
#234000
b100010 3
15
1"
#236000
05
0"
#238000
b100011 3
15
1"
#240000
05
0"
b1110 #
b1110 8
#242000
b100100 3
15
1"
#244000
05
0"
#246000
b100101 3
15
1"
#248000
05
0"
#250000
1,
1/
b100110 3
b1110 .
b1110 0
b1110 9
15
1"
1'
#252000
05
0"
#254000
14
b1 7
b1111111111110000 6
b100111 3
15
1"
#256000
05
0"
#258000
b1111111111110001 6
04
b0 3
15
1"
#260000
05
0"
0'
#262000
b1111111111110010 6
b1 3
15
1"
#264000
05
0"
#266000
b1111111111110011 6
b10 3
15
1"
#268000
05
0"
#270000
b1111111111110100 6
b11 3
15
1"
#272000
05
0"
#274000
b1111111111110101 6
b100 3
15
1"
#276000
05
0"
#278000
b1111111111110110 6
b101 3
15
1"
#280000
05
0"
#282000
b1111111111110111 6
b110 3
15
1"
#284000
05
0"
#286000
b1111111111111000 6
b111 3
15
1"
#288000
05
0"
#290000
b1111111111111001 6
b1000 3
15
1"
#292000
05
0"
#294000
b1111111111111010 6
b1001 3
15
1"
#296000
05
0"
#298000
b1111111111111011 6
b1010 3
15
1"
#300000
05
0"
#302000
b1111111111111100 6
b1011 3
15
1"
#304000
05
0"
#306000
b1111111111111101 6
b1100 3
15
1"
#308000
05
0"
#310000
b1111111111111110 6
b1101 3
15
1"
#312000
05
0"
#314000
b1111111111111111 6
b1110 3
15
1"
#316000
05
0"
#318000
b10 *
1+
b11 7
b0 6
b1111 3
15
1"
#320000
05
0"
#322000
0,
b1 7
b1111111111110000 6
0+
b1 *
1(
b10000 3
b1100 .
b1100 0
b1100 9
15
1"
#324000
05
0"
#326000
1:
b0 *
0(
b1111111111110001 6
b1101 .
b1101 0
b1101 9
b10001 3
15
1"
#328000
05
0"
#330000
b1111111111110010 6
b10010 3
15
1"
b1100 #
b1100 8
#332000
05
0"
#334000
b1111111111110011 6
b10011 3
15
1"
#336000
05
0"
#338000
b1111111111110100 6
b10100 3
15
1"
#340000
05
0"
1'
#342000
0:
b1111111111110101 6
b1100 .
b1100 0
b1100 9
b10101 3
15
1"
#344000
05
0"
#346000
b1111111111110110 6
b10110 3
15
1"
#348000
05
0"
#350000
b1111111111110111 6
b10111 3
15
1"
0'
#352000
05
0"
#354000
b1111111111111000 6
b11000 3
15
1"
#356000
05
0"
#358000
b1111111111111001 6
b11001 3
15
1"
#360000
05
0"
#362000
b1111111111111010 6
b11010 3
15
1"
#364000
05
0"
#366000
b1111111111111011 6
b11011 3
15
1"
#368000
05
0"
#370000
b1111111111111100 6
b11100 3
15
1"
#372000
05
0"
#374000
b1111111111111101 6
b11101 3
15
1"
#376000
05
0"
#378000
b1111111111111110 6
b11110 3
15
1"
#380000
05
0"
#382000
b1111111111111111 6
b11111 3
15
1"
#384000
05
0"
#386000
b10 *
1+
b11 7
b0 6
b100000 3
15
1"
#388000
05
0"
#390000
b1 7
b1111111111110000 6
0+
b1 *
1(
b100001 3
15
1"
#392000
05
0"
#394000
1:
b0 *
0(
b1111111111110001 6
b100010 3
b1101 .
b1101 0
b1101 9
15
1"
#396000
05
0"
#398000
b1111111111110010 6
b100011 3
15
1"
#400000
05
0"
#402000
b1111111111110011 6
b100100 3
15
1"
#404000
05
0"
#406000
b1111111111110100 6
b100101 3
15
1"
#408000
05
0"
#410000
b1111111111110101 6
b100110 3
15
1"
#412000
05
0"
#414000
b1111111111110110 6
b100111 3
15
1"
#416000
05
0"
#418000
b1111111111110111 6
b101000 3
15
1"
#420000
05
0"
#422000
b1111111111111000 6
b101001 3
15
1"
#424000
05
0"
#426000
b1111111111111001 6
b101010 3
15
1"
#428000
05
0"
#430000
b1111111111111010 6
b101011 3
15
1"
b100 #
b100 8
#432000
05
0"
#434000
b1111111111111011 6
b101100 3
15
1"
#436000
05
0"
#438000
b1111111111111100 6
b101101 3
15
1"
#440000
05
0"
1'
#442000
0/
0:
b1111111111111101 6
b101110 3
b100 .
b100 0
b100 9
15
1"
#444000
05
0"
#446000
b1111111111111110 6
b101111 3
15
1"
#448000
05
0"
#450000
b1111111111111111 6
b110000 3
15
1"
0'
#452000
05
0"
#454000
b10 *
1+
b11 7
b0 6
b110001 3
15
1"
#456000
05
0"
#458000
b0 7
0+
b1 *
1(
b110010 3
15
1"
#460000
05
0"
#462000
1:
b0 *
0(
b101 .
b101 0
b101 9
b110011 3
15
1"
#464000
05
0"
#466000
b110100 3
15
1"
#468000
05
0"
#470000
b110101 3
15
1"
#472000
05
0"
#474000
b110110 3
15
1"
#476000
05
0"
#478000
b110111 3
15
1"
#480000
05
0"
#482000
b111000 3
15
1"
#484000
05
0"
#486000
b111001 3
15
1"
#488000
05
0"
#490000
b111010 3
15
1"
#492000
05
0"
#494000
b111011 3
15
1"
#496000
05
0"
#498000
b111100 3
15
1"
#500000
05
0"
#502000
b111101 3
15
1"
#504000
05
0"
#506000
b111110 3
15
1"
#508000
05
0"
#510000
b111111 3
15
1"
#512000
05
0"
#514000
b1000000 3
15
1"
#516000
05
0"
#518000
b1000001 3
15
1"
#520000
05
0"
#522000
b1000010 3
15
1"
#524000
05
0"
#526000
b1000011 3
15
1"
#528000
05
0"
#530000
b1000100 3
15
1"
b1100 #
b1100 8
#532000
05
0"
#534000
b1000101 3
15
1"
#536000
05
0"
#538000
b1000110 3
15
1"
#540000
05
0"
1'
#542000
1/
0:
b1100 .
b1100 0
b1100 9
b1000111 3
15
1"
#544000
05
0"
#546000
b1001000 3
15
1"
#548000
05
0"
#550000
b1001001 3
15
1"
0'
#552000
05
0"
#554000
b1001010 3
15
1"
#556000
05
0"
#558000
b1001011 3
15
1"
#560000
05
0"
#562000
b1001100 3
15
1"
#564000
05
0"
#566000
b1001101 3
15
1"
#568000
05
0"
#570000
b1001110 3
15
1"
#572000
05
0"
#574000
b1001111 3
15
1"
#576000
05
0"
#578000
b1010000 3
15
1"
#580000
05
0"
#582000
b1010001 3
15
1"
#584000
05
0"
#586000
b1010010 3
15
1"
#588000
05
0"
#590000
b1010011 3
15
1"
#592000
05
0"
#594000
b1010100 3
15
1"
#596000
05
0"
#598000
b1010101 3
15
1"
#600000
05
0"
#602000
b1010110 3
15
1"
#604000
05
0"
#606000
b1010111 3
15
1"
#608000
05
0"
#610000
b1011000 3
15
1"
#612000
05
0"
#614000
b1011001 3
15
1"
#616000
05
0"
#618000
b1011010 3
15
1"
#620000
05
0"
#622000
b1011011 3
15
1"
#624000
05
0"
#626000
b1011100 3
15
1"
#628000
05
0"
#630000
b1011101 3
15
1"
b1000 #
b1000 8
#632000
05
0"
#634000
b1011110 3
15
1"
#636000
05
0"
#638000
b1011111 3
15
1"
#640000
05
0"
1'
#642000
0-
b1100000 3
b1000 .
b1000 0
b1000 9
15
1"
#644000
05
0"
#646000
15
1"
#648000
05
0"
#650000
15
1"
0'
#652000
05
0"
#654000
15
1"
#656000
05
0"
#658000
15
1"
#660000
05
0"
#662000
15
1"
#664000
05
0"
#666000
15
1"
#668000
05
0"
#670000
15
1"
#672000
05
0"
#674000
15
1"
#676000
05
0"
#678000
15
1"
#680000
05
0"
#682000
15
1"
#684000
05
0"
#686000
15
1"
#688000
05
0"
#690000
15
1"
#692000
05
0"
#694000
15
1"
#696000
05
0"
#698000
15
1"
#700000
05
0"
#702000
15
1"
#704000
05
0"
#706000
15
1"
#708000
05
0"
#710000
15
1"
#712000
05
0"
#714000
15
1"
#716000
05
0"
#718000
15
1"
#720000
05
0"
#722000
15
1"
#724000
05
0"
#726000
15
1"
#728000
05
0"
#730000
15
1"
#732000
05
0"
#734000
15
1"
#736000
05
0"
#738000
15
1"
#740000
05
0"
#742000
15
1"
#744000
05
0"
#746000
15
1"
#748000
05
0"
#750000
15
1"
