pacoblaze/bamse_v1/iverilog/timer/timer.v
`ifndef TIMER_V
`define TIMER_V

module timer(
	input clk_in,
	input rst, //(H)
	input [2:0] prescaler_conf, //Select between 8 possible frequencies 000 -> clk_in : 111 -> clk_in/128
	input [15:0] timer_conf, // 16 bit load value for the counter 
	input en, //enable (H)
	input go, //start (H)
	input auto_load, //automatic restart timer after rolloff (H)
	input write,
	output reg tmr_int, //roll of - interrupt 1 pulse (H)
	output reg go_clear // 1 pulse (H)
);

reg [6:0] prescaler_out;
		  
//reg prescaler_state;

always @(posedge clk_in) begin
	if (rst) begin
		prescaler_out <= 0;			
	end else begin
		if (write) begin
			prescaler_out <= 0;					
		end else begin
			prescaler_out <= prescaler_out + 1;
		end
	end
end

//Prescaler selector
reg selected_freq;

always @(*) begin
	case (prescaler_conf)
		3'b000: selected_freq = clk_in;
		3'b001: selected_freq = prescaler_out[0];
		3'b010: selected_freq = prescaler_out[1];
		3'b011: selected_freq = prescaler_out[2];
		3'b100: selected_freq = prescaler_out[3];
		3'b101: selected_freq = prescaler_out[4]; 
		3'b110: selected_freq = prescaler_out[5];
		3'b111: selected_freq = prescaler_out[6];
		default: selected_freq = clk_in;
	endcase
end

//Timer
reg [15:0] timer_count;
reg [1:0] timer_state;

parameter IDLE  = 2'b00, 
		  GO =    2'b01,
		  ROLL  = 2'b11;
		 
always @(posedge selected_freq) begin
	if (rst) begin
		timer_count <= 0;					
		tmr_int <= 0;
		timer_state <= IDLE;
		//prescaler_reset <= 0;
		go_clear <= 0;
	end else begin 
		if (en) begin
			case (timer_state)
				IDLE:	begin
							if (go) begin 
								timer_count <= timer_conf;														
								timer_state <= GO;
								//prescaler_reset <= 1;
							end 
														
							tmr_int <= 0;
						
						end
				GO:		begin 
							//prescaler_reset <= 0;
							timer_count <= timer_count + 1;
							
							if (timer_count == 16'hffff) begin
								timer_state <= ROLL;
								go_clear <= 1;
							end							
							
							tmr_int <= 0;													
						end
				ROLL: 	begin
							tmr_int <= 1;
							go_clear <= 0;
							if (auto_load) begin
								timer_count <= timer_conf;														
								timer_state <= GO;
							end else begin
								timer_state <= IDLE;
							end
						end				
			endcase
		end else begin
			timer_state <= IDLE;
		end
	
	end
end

endmodule

/**************************/
/*    TIMER BAMSE         */
/**************************/

// Configuration word (config_in and config_out)
//      B7       B6        B5       B4        B3        B2        B1        B0
//   	-        PS2      PS1       PS0      AUTO_LD    EN        GO      INT_TMR
//
// Note: GO and INT_TMR R&W bits that are set/cleared by the timer.
// 

module TIMER_BAMSE (
	input clk,
	input rst, //(H)
	input [15:0] timer_conf, // 16 bit load value for the counter 
	input [7:0] address,
	input [7:0] config_in,
	output [7:0] config_out,
	input ren,
	input wen	
);

parameter ADDR = 8'h00; // This same register address is used for read and write

reg  [7:0] timer_config_reg;
wire [1:0] mask_reset;
wire go_clear;
wire tmr_int;

//outputs from timer
assign mask_reset[0] = tmr_int;
assign mask_reset[1] = go_clear;

wire update_config;
assign update_config = ((address == ADDR) & wen)? 1'b1 : 1'b0;

always @(posedge clk) begin
	if (rst) begin
		timer_config_reg <= 0;
	end else if (|mask_reset) begin // Signals from timer module 
		if (mask_reset[0]) timer_config_reg[0] <= 1; // To interrupt out
		if (mask_reset[1]) timer_config_reg[1] <= 0; // To GO
	//	end	else if (address == ADDR) begin //signals written from software
	//	if (wen) begin
	end else if (update_config) begin
			timer_config_reg <= config_in;
	end				
end

assign config_out = timer_config_reg;

wire go, en, auto_load;
wire [2:0] prescaler_conf;

assign go = config_out[1];
assign en = config_out[2];
assign auto_load = config_out[3];
assign prescaler_conf[2:0] = config_out[6:4];


timer tmt(
	.clk_in(clk),
	.rst(rst),
	.prescaler_conf(prescaler_conf),
	.timer_conf(timer_conf),
	.en(en),
	.go(go),
	.auto_load(auto_load),	
	.write(wen),
	.tmr_int(tmr_int),
	.go_clear(go_clear)
);

endmodule

`endif

pacoblaze/bamse_v1/iverilog/timer/timer_tb.v
//timer_tb.v

`timescale 1ns/1ps

`include "timer.v"

module timer_tb();

reg clk;
reg rst;
reg [2:0] prescaler_conf;
reg [15:0] timer_conf; 
reg en; //enable (H)
reg go; //start (H)
reg auto_load; //automatic restart timer after rolloff (H)
reg int;
reg [7:0] address;
wire [7:0] config_in;
wire [7:0] config_out;
reg ren;
reg wen;

wire interrupt;

assign interrupt = config_out[0];

assign config_in = {{1'b0},prescaler_conf,auto_load,en,go,int};
parameter ADDR=8'h00;

TIMER_BAMSE #(.ADDR(8'h00)) dut(
	.clk(clk),
	.rst(rst),	
	.timer_conf(timer_conf),
	.address(address),
	.config_in(config_in),
	.config_out(config_out),
	.ren(ren),
	.wen(wen)
);

always #(2) clk = ~clk;

initial begin
	$dumpfile("dump.vcd");
	$dumpvars(-1,dut,config_in,config_out,interrupt);
	
	en = 0;
	clk = 0;
	rst = 0;
	prescaler_conf = 0;
	timer_conf = 16'hfff0;
	en = 0;
	go = 0;
	auto_load = 0;
	address = 8'h00;
	ren = 0;
	wen = 0;
	int = 0;
		
	
	#10 rst = 1;
	#10 rst = 0;
	
	//task1;
	task2;
	
	#(100) $finish;
end

task task1; //selected_clk = 000
	begin
	#50 en = 1;
	#10 go = 1;
	#10 wen = 1;
	#10 go = 0; wen = 0;
	
	#80 wen = 1; 
	#10 wen = 0;
	
	#50 auto_load = 1; go = 1;
	#10 wen = 1;
	#10 wen = 0;
	
	#70 go = 0; int = 0;
	#10 wen = 1;
	#10 wen = 0;
	
	#80 auto_load = 0; int = 0;
	#10 wen = 1;
	#10 wen = 0;
	
	#80 auto_load = 1;
	#10 wen = 1;
	#10 wen = 0;
	
	#80 en = 0;
	#10 wen = 1;
	#10 wen = 0;
	
	end
endtask

task task2; //selected_clk = 001
	begin
	#10 prescaler_conf = 3'b001;
	#50 en = 1;
	#10 go = 1;
	#10 wen = 1;
	#10 go = 0; wen = 0;
	
	#160 wen = 1; 
	#10 wen = 0;
	
	#100 auto_load = 1; go = 1;
	#10 wen = 1;
	#10 wen = 0;
	
	#160 go = 0; int = 0;
	#10 wen = 1;
	#10 wen = 0;
	
	#160 auto_load = 0; int = 0;
	#10 wen = 1;
	#10 wen = 0;
	
	#160 auto_load = 1;
	#10 wen = 1;
	#10 wen = 0;
	
	#160 en = 0;
	#10 wen = 1;
	#10 wen = 0;
	
	end
endtask


endmodule

pacoblaze/bamse_v1/iverilog/timer/dump.vcd
$date
	Fri Oct  4 12:02:50 2019
$end
$version
	Icarus Verilog
$end
$timescale
	1ps
$end
$scope module timer_tb $end
$scope module dut $end
$var wire 8 ! address [7:0] $end
$var wire 1 " clk $end
$var wire 8 # config_in [7:0] $end
$var wire 1 $ ren $end
$var wire 1 % rst $end
$var wire 16 & timer_conf [15:0] $end
$var wire 1 ' wen $end
$var wire 1 ( update_config $end
$var wire 1 ) tmr_int $end
$var wire 3 * prescaler_conf [2:0] $end
$var wire 2 + mask_reset [1:0] $end
$var wire 1 , go_clear $end
$var wire 1 - go $end
$var wire 1 . en $end
$var wire 8 / config_out [7:0] $end
$var wire 1 0 auto_load $end
$var reg 8 1 timer_config_reg [7:0] $end
$scope module tmt $end
$var wire 1 0 auto_load $end
$var wire 1 " clk_in $end
$var wire 1 . en $end
$var wire 1 - go $end
$var wire 3 2 prescaler_conf [2:0] $end
$var wire 1 % rst $end
$var wire 16 3 timer_conf [15:0] $end
$var wire 1 ' write $end
$var reg 1 , go_clear $end
$var reg 7 4 prescaler_out [6:0] $end
$var reg 1 5 selected_freq $end
$var reg 16 6 timer_count [15:0] $end
$var reg 2 7 timer_state [1:0] $end
$var reg 1 ) tmr_int $end
$upscope $end
$upscope $end
$upscope $end
$scope module timer_tb $end
$var wire 8 8 config_in [7:0] $end
$upscope $end
$scope module timer_tb $end
$var wire 8 9 config_out [7:0] $end
$upscope $end
$scope module timer_tb $end
$var wire 1 : interrupt $end
$upscope $end
$enddefinitions $end
#0
$dumpvars
x:
bx 9
b0 8
bx 7
bx 6
05
bx 4
b1111111111110000 3
bx 2
bx 1
x0
bx /
x.
x-
x,
bx +
bx *
x)
0(
0'
b1111111111110000 &
0%
0$
b0 #
0"
b0 !
$end
#2000
b0 7
15
1"
#4000
05
0"
#6000
15
1"
#8000
05
0"
#10000
0-
0.
00
b0 *
b0 2
0:
0,
b0 +
0)
b0 6
b0 4
b0 /
b0 1
b0 9
15
1"
1%
#12000
05
0"
#14000
15
1"
#16000
05
0"
#18000
15
1"
#20000
05
0"
0%
#22000
b1 4
15
1"
#24000
05
0"
#26000
b10 4
15
1"
#28000
05
0"
#30000
b11 4
15
1"
b10000 #
b10000 8
#32000
05
0"
#34000
b100 4
15
1"
#36000
05
0"
#38000
b101 4
15
1"
#40000
05
0"
#42000
b110 4
15
1"
#44000
05
0"
#46000
b111 4
15
1"
#48000
05
0"
#50000
b1000 4
15
1"
#52000
05
0"
#54000
b1001 4
15
1"
#56000
05
0"
#58000
b1010 4
15
1"
#60000
05
0"
#62000
b1011 4
15
1"
#64000
05
0"
#66000
b1100 4
15
1"
#68000
05
0"
#70000
b1101 4
15
1"
#72000
05
0"
#74000
b1110 4
15
1"
#76000
05
0"
#78000
b1111 4
15
1"
#80000
05
0"
b10100 #
b10100 8
#82000
b10000 4
15
1"
#84000
05
0"
#86000
b10001 4
15
1"
#88000
05
0"
#90000
b10010 4
15
1"
b10110 #
b10110 8
#92000
05
0"
#94000
b10011 4
15
1"
#96000
05
0"
#98000
b10100 4
15
1"
#100000
1(
05
0"
1'
#102000
1-
1.
b1 *
b1 2
b10110 /
b10110 1
b10110 9
b0 4
05
1"
#104000
0"
#106000
1"
#108000
0"
#110000
0-
15
b10100 /
b10100 1
b10100 9
b1 4
0(
1"
0'
b10100 #
b10100 8
#112000
0"
#114000
05
b10 4
1"
#116000
0"
#118000
15
b11 4
1"
#120000
0"
#122000
05
b100 4
1"
#124000
0"
#126000
15
b101 4
1"
#128000
0"
#130000
05
b110 4
1"
#132000
0"
#134000
15
b111 4
1"
#136000
0"
#138000
05
b1000 4
1"
#140000
0"
#142000
15
b1001 4
1"
#144000
0"
#146000
05
b1010 4
1"
#148000
0"
#150000
15
b1011 4
1"
#152000
0"
#154000
05
b1100 4
1"
#156000
0"
#158000
15
b1101 4
1"
#160000
0"
#162000
05
b1110 4
1"
#164000
0"
#166000
15
b1111 4
1"
#168000
0"
#170000
05
b10000 4
1"
#172000
0"
#174000
15
b10001 4
1"
#176000
0"
#178000
05
b10010 4
1"
#180000
0"
#182000
15
b10011 4
1"
#184000
0"
#186000
05
b10100 4
1"
#188000
0"
#190000
15
b10101 4
1"
#192000
0"
#194000
05
b10110 4
1"
#196000
0"
#198000
15
b10111 4
1"
#200000
0"
#202000
05
b11000 4
1"
#204000
0"
#206000
15
b11001 4
1"
#208000
0"
#210000
05
b11010 4
1"
#212000
0"
#214000
15
b11011 4
1"
#216000
0"
#218000
05
b11100 4
1"
#220000
0"
#222000
15
b11101 4
1"
#224000
0"
#226000
05
b11110 4
1"
#228000
0"
#230000
15
b11111 4
1"
#232000
0"
#234000
05
b100000 4
1"
#236000
0"
#238000
15
b100001 4
1"
#240000
0"
#242000
05
b100010 4
1"
#244000
0"
#246000
15
b100011 4
1"
#248000
0"
#250000
05
b100100 4
1"
#252000
0"
#254000
15
b100101 4
1"
#256000
0"
#258000
05
b100110 4
1"
#260000
0"
#262000
15
b100111 4
1"
#264000
0"
#266000
05
b101000 4
1"
#268000
0"
#270000
b0 4
1(
1"
1'
#272000
0"
#274000
1"
#276000
0"
#278000
1"
#280000
0(
0"
0'
#282000
15
b1 4
1"
#284000
0"
#286000
05
b10 4
1"
#288000
0"
#290000
15
b11 4
1"
#292000
0"
#294000
05
b100 4
1"
#296000
0"
#298000
15
b101 4
1"
#300000
0"
#302000
05
b110 4
1"
#304000
0"
#306000
15
b111 4
1"
#308000
0"
#310000
05
b1000 4
1"
#312000
0"
#314000
15
b1001 4
1"
#316000
0"
#318000
05
b1010 4
1"
#320000
0"
#322000
15
b1011 4
1"
#324000
0"
#326000
05
b1100 4
1"
#328000
0"
#330000
15
b1101 4
1"
#332000
0"
#334000
05
b1110 4
1"
#336000
0"
#338000
15
b1111 4
1"
#340000
0"
#342000
05
b10000 4
1"
#344000
0"
#346000
15
b10001 4
1"
#348000
0"
#350000
05
b10010 4
1"
#352000
0"
#354000
15
b10011 4
1"
#356000
0"
#358000
05
b10100 4
1"
#360000
0"
#362000
15
b10101 4
1"
#364000
0"
#366000
05
b10110 4
1"
#368000
0"
#370000
15
b10111 4
1"
#372000
0"
#374000
05
b11000 4
1"
#376000
0"
#378000
15
b11001 4
1"
#380000
0"
b11110 #
b11110 8
#382000
05
b11010 4
1"
#384000
0"
#386000
15
b11011 4
1"
#388000
0"
#390000
05
b0 4
1(
1"
1'
#392000
0"
#394000
1-
10
b11110 /
b11110 1
b11110 9
1"
#396000
0"
#398000
1"
#400000
0(
0"
0'
#402000
b1 7
b1111111111110000 6
15
b1 4
1"
#404000
0"
#406000
05
b10 4
1"
#408000
0"
#410000
b1111111111110001 6
15
b11 4
1"
#412000
0"
#414000
05
b100 4
1"
#416000
0"
#418000
b1111111111110010 6
15
b101 4
1"
#420000
0"
#422000
05
b110 4
1"
#424000
0"
#426000
b1111111111110011 6
15
b111 4
1"
#428000
0"
#430000
05
b1000 4
1"
#432000
0"
#434000
b1111111111110100 6
15
b1001 4
1"
#436000
0"
#438000
05
b1010 4
1"
#440000
0"
#442000
b1111111111110101 6
15
b1011 4
1"
#444000
0"
#446000
05
b1100 4
1"
#448000
0"
#450000
b1111111111110110 6
15
b1101 4
1"
#452000
0"
#454000
05
b1110 4
1"
#456000
0"
#458000
b1111111111110111 6
15
b1111 4
1"
#460000
0"
#462000
05
b10000 4
1"
#464000
0"
#466000
b1111111111111000 6
15
b10001 4
1"
#468000
0"
#470000
05
b10010 4
1"
#472000
0"
#474000
b1111111111111001 6
15
b10011 4
1"
#476000
0"
#478000
05
b10100 4
1"
#480000
0"
#482000
b1111111111111010 6
15
b10101 4
1"
#484000
0"
#486000
05
b10110 4
1"
#488000
0"
#490000
b1111111111111011 6
15
b10111 4
1"
#492000
0"
#494000
05
b11000 4
1"
#496000
0"
#498000
b1111111111111100 6
15
b11001 4
1"
#500000
0"
#502000
05
b11010 4
1"
#504000
0"
#506000
b1111111111111101 6
15
b11011 4
1"
#508000
0"
#510000
05
b11100 4
1"
#512000
0"
#514000
b1111111111111110 6
15
b11101 4
1"
#516000
0"
#518000
05
b11110 4
1"
#520000
0"
#522000
b1111111111111111 6
15
b11111 4
1"
#524000
0"
#526000
05
b100000 4
1"
#528000
0"
#530000
b10 +
1,
b11 7
b0 6
15
b100001 4
1"
#532000
0"
#534000
0-
05
b11100 /
b11100 1
b11100 9
b100010 4
1"
#536000
0"
#538000
b1 7
b1111111111110000 6
0,
b1 +
1)
15
b100011 4
1"
#540000
0"
#542000
1:
05
b11101 /
b11101 1
b11101 9
b100100 4
1"
#544000
0"
#546000
b0 +
0)
b1111111111110001 6
15
b100101 4
1"
#548000
0"
#550000
05
b100110 4
1"
#552000
0"
#554000
b1111111111110010 6
15
b100111 4
1"
#556000
0"
#558000
05
b101000 4
1"
#560000
0"
b11100 #
b11100 8
#562000
b1111111111110011 6
15
b101001 4
1"
#564000
0"
#566000
05
b101010 4
1"
#568000
0"
#570000
b0 4
1(
1"
1'
#572000
0"
#574000
0:
b11100 /
b11100 1
b11100 9
1"
#576000
0"
#578000
1"
#580000
0(
0"
0'
#582000
b1111111111110100 6
15
b1 4
1"
#584000
0"
#586000
05
b10 4
1"
#588000
0"
#590000
b1111111111110101 6
15
b11 4
1"
#592000
0"
#594000
05
b100 4
1"
#596000
0"
#598000
b1111111111110110 6
15
b101 4
1"
#600000
0"
#602000
05
b110 4
1"
#604000
0"
#606000
b1111111111110111 6
15
b111 4
1"
#608000
0"
#610000
05
b1000 4
1"
#612000
0"
#614000
b1111111111111000 6
15
b1001 4
1"
#616000
0"
#618000
05
b1010 4
1"
#620000
0"
#622000
b1111111111111001 6
15
b1011 4
1"
#624000
0"
#626000
05
b1100 4
1"
#628000
0"
#630000
b1111111111111010 6
15
b1101 4
1"
#632000
0"
#634000
05
b1110 4
1"
#636000
0"
#638000
b1111111111111011 6
15
b1111 4
1"
#640000
0"
#642000
05
b10000 4
1"
#644000
0"
#646000
b1111111111111100 6
15
b10001 4
1"
#648000
0"
#650000
05
b10010 4
1"
#652000
0"
#654000
b1111111111111101 6
15
b10011 4
1"
#656000
0"
#658000
05
b10100 4
1"
#660000
0"
#662000
b1111111111111110 6
15
b10101 4
1"
#664000
0"
#666000
05
b10110 4
1"
#668000
0"
#670000
b1111111111111111 6
15
b10111 4
1"
#672000
0"
#674000
05
b11000 4
1"
#676000
0"
#678000
b10 +
1,
b11 7
b0 6
15
b11001 4
1"
#680000
0"
#682000
05
b11010 4
1"
#684000
0"
#686000
b1 7
b1111111111110000 6
0,
b1 +
1)
15
b11011 4
1"
#688000
0"
#690000
05
1:
b11100 4
b11101 /
b11101 1
b11101 9
1"
#692000
0"
#694000
b0 +
0)
b1111111111110001 6
15
b11101 4
1"
#696000
0"
#698000
05
b11110 4
1"
#700000
0"
#702000
b1111111111110010 6
15
b11111 4
1"
#704000
0"
#706000
05
b100000 4
1"
#708000
0"
#710000
b1111111111110011 6
15
b100001 4
1"
#712000
0"
#714000
05
b100010 4
1"
#716000
0"
#718000
b1111111111110100 6
15
b100011 4
1"
#720000
0"
#722000
05
b100100 4
1"
#724000
0"
#726000
b1111111111110101 6
15
b100101 4
1"
#728000
0"
#730000
05
b100110 4
1"
#732000
0"
#734000
b1111111111110110 6
15
b100111 4
1"
#736000
0"
#738000
05
b101000 4
1"
#740000
0"
b10100 #
b10100 8
#742000
b1111111111110111 6
15
b101001 4
1"
#744000
0"
#746000
05
b101010 4
1"
#748000
0"
#750000
b0 4
1(
1"
1'
#752000
0"
#754000
00
0:
b10100 /
b10100 1
b10100 9
1"
#756000
0"
#758000
1"
#760000
0(
0"
0'
#762000
b1111111111111000 6
15
b1 4
1"
#764000
0"
#766000
05
b10 4
1"
#768000
0"
#770000
b1111111111111001 6
15
b11 4
1"
#772000
0"
#774000
05
b100 4
1"
#776000
0"
#778000
b1111111111111010 6
15
b101 4
1"
#780000
0"
#782000
05
b110 4
1"
#784000
0"
#786000
b1111111111111011 6
15
b111 4
1"
#788000
0"
#790000
05
b1000 4
1"
#792000
0"
#794000
b1111111111111100 6
15
b1001 4
1"
#796000
0"
#798000
05
b1010 4
1"
#800000
0"
#802000
b1111111111111101 6
15
b1011 4
1"
#804000
0"
#806000
05
b1100 4
1"
#808000
0"
#810000
b1111111111111110 6
15
b1101 4
1"
#812000
0"
#814000
05
b1110 4
1"
#816000
0"
#818000
b1111111111111111 6
15
b1111 4
1"
#820000
0"
#822000
05
b10000 4
1"
#824000
0"
#826000
b10 +
1,
b11 7
b0 6
15
b10001 4
1"
#828000
0"
#830000
05
b10010 4
1"
#832000
0"
#834000
b0 7
0,
b1 +
1)
15
b10011 4
1"
#836000
0"
#838000
1:
05
b10101 /
b10101 1
b10101 9
b10100 4
1"
#840000
0"
#842000
b0 +
0)
15
b10101 4
1"
#844000
0"
#846000
05
b10110 4
1"
#848000
0"
#850000
15
b10111 4
1"
#852000
0"
#854000
05
b11000 4
1"
#856000
0"
#858000
15
b11001 4
1"
#860000
0"
#862000
05
b11010 4
1"
#864000
0"
#866000
15
b11011 4
1"
#868000
0"
#870000
05
b11100 4
1"
#872000
0"
#874000
15
b11101 4
1"
#876000
0"
#878000
05
b11110 4
1"
#880000
0"
#882000
15
b11111 4
1"
#884000
0"
#886000
05
b100000 4
1"
#888000
0"
#890000
15
b100001 4
1"
#892000
0"
#894000
05
b100010 4
1"
#896000
0"
#898000
15
b100011 4
1"
#900000
0"
#902000
05
b100100 4
1"
#904000
0"
#906000
15
b100101 4
1"
#908000
0"
#910000
05
b100110 4
1"
#912000
0"
#914000
15
b100111 4
1"
#916000
0"
#918000
05
b101000 4
1"
#920000
0"
b11100 #
b11100 8
#922000
15
b101001 4
1"
#924000
0"
#926000
05
b101010 4
1"
#928000
0"
#930000
b0 4
1(
1"
1'
#932000
0"
#934000
10
0:
b11100 /
b11100 1
b11100 9
1"
#936000
0"
#938000
1"
#940000
0(
0"
0'
#942000
15
b1 4
1"
#944000
0"
#946000
05
b10 4
1"
#948000
0"
#950000
15
b11 4
1"
#952000
0"
#954000
05
b100 4
1"
#956000
0"
#958000
15
b101 4
1"
#960000
0"
#962000
05
b110 4
1"
#964000
0"
#966000
15
b111 4
1"
#968000
0"
#970000
05
b1000 4
1"
#972000
0"
#974000
15
b1001 4
1"
#976000
0"
#978000
05
b1010 4
1"
#980000
0"
#982000
15
b1011 4
1"
#984000
0"
#986000
05
b1100 4
1"
#988000
0"
#990000
15
b1101 4
1"
#992000
0"
#994000
05
b1110 4
1"
#996000
0"
#998000
15
b1111 4
1"
#1000000
0"
#1002000
05
b10000 4
1"
#1004000
0"
#1006000
15
b10001 4
1"
#1008000
0"
#1010000
05
b10010 4
1"
#1012000
0"
#1014000
15
b10011 4
1"
#1016000
0"
#1018000
05
b10100 4
1"
#1020000
0"
#1022000
15
b10101 4
1"
#1024000
0"
#1026000
05
b10110 4
1"
#1028000
0"
#1030000
15
b10111 4
1"
#1032000
0"
#1034000
05
b11000 4
1"
#1036000
0"
#1038000
15
b11001 4
1"
#1040000
0"
#1042000
05
b11010 4
1"
#1044000
0"
#1046000
15
b11011 4
1"
#1048000
0"
#1050000
05
b11100 4
1"
#1052000
0"
#1054000
15
b11101 4
1"
#1056000
0"
#1058000
05
b11110 4
1"
#1060000
0"
#1062000
15
b11111 4
1"
#1064000
0"
#1066000
05
b100000 4
1"
#1068000
0"
#1070000
15
b100001 4
1"
#1072000
0"
#1074000
05
b100010 4
1"
#1076000
0"
#1078000
15
b100011 4
1"
#1080000
0"
#1082000
05
b100100 4
1"
#1084000
0"
#1086000
15
b100101 4
1"
#1088000
0"
#1090000
05
b100110 4
1"
#1092000
0"
#1094000
15
b100111 4
1"
#1096000
0"
#1098000
05
b101000 4
1"
#1100000
0"
b11000 #
b11000 8
#1102000
15
b101001 4
1"
#1104000
0"
#1106000
05
b101010 4
1"
#1108000
0"
#1110000
b0 4
1(
1"
1'
#1112000
0"
#1114000
0.
b11000 /
b11000 1
b11000 9
1"
#1116000
0"
#1118000
1"
#1120000
0(
0"
0'
#1122000
15
b1 4
1"
#1124000
0"
#1126000
05
b10 4
1"
#1128000
0"
#1130000
15
b11 4
1"
#1132000
0"
#1134000
05
b100 4
1"
#1136000
0"
#1138000
15
b101 4
1"
#1140000
0"
#1142000
05
b110 4
1"
#1144000
0"
#1146000
15
b111 4
1"
#1148000
0"
#1150000
05
b1000 4
1"
#1152000
0"
#1154000
15
b1001 4
1"
#1156000
0"
#1158000
05
b1010 4
1"
#1160000
0"
#1162000
15
b1011 4
1"
#1164000
0"
#1166000
05
b1100 4
1"
#1168000
0"
#1170000
15
b1101 4
1"
#1172000
0"
#1174000
05
b1110 4
1"
#1176000
0"
#1178000
15
b1111 4
1"
#1180000
0"
#1182000
05
b10000 4
1"
#1184000
0"
#1186000
15
b10001 4
1"
#1188000
0"
#1190000
05
b10010 4
1"
#1192000
0"
#1194000
15
b10011 4
1"
#1196000
0"
#1198000
05
b10100 4
1"
#1200000
0"
#1202000
15
b10101 4
1"
#1204000
0"
#1206000
05
b10110 4
1"
#1208000
0"
#1210000
15
b10111 4
1"
#1212000
0"
#1214000
05
b11000 4
1"
#1216000
0"
#1218000
15
b11001 4
1"
