pacoblaze/bamse_v1/iverilog/timer/timer.v
`ifndef TIMER_V
`define TIMER_V

module timer(
	input clk_in,
	input rst, //(H)
	input [2:0] prescaler_conf, //Select between 8 possible frequencies 000 -> clk_in : 111 -> clk_in/128
	input [15:0] timer_conf, // 16 bit load value for the counter 
	input en, //enable (H)
	input go, //start (H)
	input auto_load, //automatic restart timer after rolloff (H)
	input write,
	output reg tmr_int, //roll of - interrupt 1 pulse (H)
	output reg go_clear // 1 pulse (H)
);

reg [6:0] prescaler_out;
		  
//reg prescaler_state;

always @(posedge clk_in) begin
	if (rst) begin
		prescaler_out <= 0;			
	end else begin
		if (write) begin
			prescaler_out <= 0;					
		end else begin
			prescaler_out <= prescaler_out + 1;
		end
	end
end

//Prescaler selector
reg selected_freq;

always @(*) begin
	case (prescaler_conf)
		3'b000: selected_freq = clk_in;
		3'b001: selected_freq = prescaler_out[0];
		3'b010: selected_freq = prescaler_out[1];
		3'b011: selected_freq = prescaler_out[2];
		3'b100: selected_freq = prescaler_out[3];
		3'b101: selected_freq = prescaler_out[4]; 
		3'b110: selected_freq = prescaler_out[5];
		3'b111: selected_freq = prescaler_out[6];
		default: selected_freq = clk_in;
	endcase
end

//Timer
reg [15:0] timer_count;
reg [1:0] timer_state;

parameter IDLE  = 2'b00, 
		  GO =    2'b01,
		  ROLL  = 2'b11;
		 
always @(posedge selected_freq) begin
	if (rst) begin
		timer_count <= 0;					
		tmr_int <= 0;
		timer_state <= IDLE;
		//prescaler_reset <= 0;
		go_clear <= 0;
	end else begin 
		if (en) begin
			case (timer_state)
				IDLE:	begin
							if (go) begin 
								timer_count <= timer_conf;														
								timer_state <= GO;
								//prescaler_reset <= 1;
							end 
														
							tmr_int <= 0;
						
						end
				GO:		begin 
							//prescaler_reset <= 0;
							timer_count <= timer_count + 1;
							
							if (timer_count == 16'hffff) begin
								timer_state <= ROLL;
								go_clear <= 1;
							end							
							
							tmr_int <= 0;													
						end
				ROLL: 	begin
							tmr_int <= 1;
							go_clear <= 0;
							if (auto_load) begin
								timer_count <= timer_conf;														
								timer_state <= GO;
							end else begin
								timer_state <= IDLE;
							end
						end				
			endcase
		end else begin
			timer_state <= IDLE;
		end
	
	end
end

endmodule

/**************************/
/*    TIMER BAMSE         */
/**************************/

// Configuration word (both input and output)
//      B7       B6        B5       B4        B3        B2        B1        B0
//   	-        PS2      PS1       PS0      AUTO_LD    EN        GO      INT_TMR
//
// Note: GO and INT_TMR are R&W bits that are set/cleared by the timer.
// 

module TIMER_BAMSE (
	input clk,
	input rst, //(H)
	input [15:0] timer_conf, // 16 bit load value for the counter 
	input [7:0] address,
	input [7:0] config_in,
	output [7:0] config_out,
	input ren,
	input wen	
);

parameter ADDR = 8'h00; // This same register address is used for read and write

reg  [7:0] timer_config_reg;
wire [1:0] mask_reset;

wire go_clear;
reg  go_clear_sync;
wire go_clear_pulse;

wire tmr_int;
reg tmr_int_sync;
wire tmr_int_pulse;

//synchronize signals from timer

always @(posedge clk) begin
	if (rst) begin
		go_clear_sync <= 0;
		tmr_int_sync <= 0;
	end else begin
		go_clear_sync <= go_clear;
		tmr_int_sync <= tmr_int;	
	end		
end

assign go_clear_pulse = go_clear & (~go_clear_sync);
assign tmr_int_pulse = tmr_int & (~tmr_int_sync);



//outputs from timer
assign mask_reset[0] = tmr_int_pulse;
assign mask_reset[1] = go_clear_pulse;

wire update_config;
assign update_config = ((address == ADDR) & wen)? 1'b1 : 1'b0;

always @(posedge clk) begin
	if (rst) begin
		timer_config_reg <= 0;
	end else if (|mask_reset) begin // Signals from timer module 
		if (mask_reset[0]) timer_config_reg[0] <= 1; // To interrupt out
		if (mask_reset[1]) timer_config_reg[1] <= 0; // To GO
	//	end	else if (address == ADDR) begin //signals written from software
	//	if (wen) begin
	end else if (update_config) begin
			timer_config_reg <= config_in;
	end				
end

assign config_out = timer_config_reg;

wire go, en, auto_load;
wire [2:0] prescaler_conf;

assign go = config_out[1];
assign en = config_out[2];
assign auto_load = config_out[3];
assign prescaler_conf[2:0] = config_out[6:4];


timer tmt(
	.clk_in(clk),
	.rst(rst),
	.prescaler_conf(prescaler_conf),
	.timer_conf(timer_conf),
	.en(en),
	.go(go),
	.auto_load(auto_load),	
	.write(wen),
	.tmr_int(tmr_int),
	.go_clear(go_clear)
);

endmodule

`endif

pacoblaze/bamse_v1/iverilog/timer/timer_tb.v
//timer_tb.v

`timescale 1ns/1ps

`include "timer.v"

module timer_tb();

reg clk;
reg rst;
reg [2:0] prescaler_conf;
reg [15:0] timer_conf; 
reg en; //enable (H)
reg go; //start (H)
reg auto_load; //automatic restart timer after rolloff (H)
reg int;
reg [7:0] address;
wire [7:0] config_in;
wire [7:0] config_out;
reg ren;
reg wen;

wire interrupt;

assign interrupt = config_out[0];

assign config_in = {{1'b0},prescaler_conf,auto_load,en,go,int};
parameter ADDR=8'h01;
parameter pres_factor = 3;

TIMER_BAMSE #(.ADDR(ADDR)) dut(
	.clk(clk),
	.rst(rst),	
	.timer_conf(timer_conf),
	.address(address),
	.config_in(config_in),
	.config_out(config_out),
	.ren(ren),
	.wen(wen)
);

always #(2) clk = ~clk;

initial begin
	$dumpfile("dump.vcd");
	$dumpvars(-1,dut,config_in,config_out,interrupt);
	
	en = 0;
	clk = 0;
	rst = 0;
	prescaler_conf = 0;
	timer_conf = 16'hfff0;
	en = 0;
	go = 0;
	auto_load = 0;
	address = 8'h01;
	ren = 0;
	wen = 0;
	int = 0;
		
	
	#10 rst = 1;
	#10 rst = 0;
	
	//task1;
	task2;
	
	#(100) $finish;
end

task task1; //selected_clk = 000
	begin
	#50 en = 1;
	#10 go = 1;
	#10 wen = 1;
	#10 go = 0; wen = 0;
	
	#80 wen = 1; 
	#10 wen = 0;
	
	#50 auto_load = 1; go = 1;
	#10 wen = 1;
	#10 wen = 0;
	
	#70 go = 0; int = 0;
	#10 wen = 1;
	#10 wen = 0;
	
	#80 auto_load = 0; int = 0;
	#10 wen = 1;
	#10 wen = 0;
	
	#80 auto_load = 1;
	#10 wen = 1;
	#10 wen = 0;
	
	#80 en = 0;
	#10 wen = 1;
	#10 wen = 0;
	
	end
endtask

task task2; //selected_clk = 001
	begin
	#10 prescaler_conf = pres_factor;
	#50 en = 1;
	#10 go = 1;
	#10 wen = 1;
	#10 wen = 0;
	
	#(90*pres_factor) wen = 1; 
	#10 wen = 0;
	
	#(100*pres_factor) auto_load = 1; go = 1;
	#10 wen = 1;
	#10 wen = 0;
	
	#(90*pres_factor) go = 0; int = 0;
	#10 wen = 1;
	#10 wen = 0;
	
	#(90*pres_factor) auto_load = 0; int = 0;
	#10 wen = 1;
	#10 wen = 0;
	
	#(90*pres_factor) auto_load = 1;
	#10 wen = 1;
	#10 wen = 0;
	
	#(90*pres_factor) en = 0;
	#10 wen = 1;
	#10 wen = 0;
	
	end
endtask



endmodule

pacoblaze/bamse_v1/iverilog/timer/dump.vcd
$date
	Fri Oct  4 22:12:53 2019
$end
$version
	Icarus Verilog
$end
$timescale
	1ps
$end
$scope module timer_tb $end
$scope module dut $end
$var wire 8 ! address [7:0] $end
$var wire 1 " clk $end
$var wire 8 # config_in [7:0] $end
$var wire 1 $ go_clear_pulse $end
$var wire 1 % ren $end
$var wire 1 & rst $end
$var wire 16 ' timer_conf [15:0] $end
$var wire 1 ( tmr_int_pulse $end
$var wire 1 ) wen $end
$var wire 1 * update_config $end
$var wire 1 + tmr_int $end
$var wire 3 , prescaler_conf [2:0] $end
$var wire 2 - mask_reset [1:0] $end
$var wire 1 . go_clear $end
$var wire 1 / go $end
$var wire 1 0 en $end
$var wire 8 1 config_out [7:0] $end
$var wire 1 2 auto_load $end
$var reg 1 3 go_clear_sync $end
$var reg 8 4 timer_config_reg [7:0] $end
$var reg 1 5 tmr_int_sync $end
$scope module tmt $end
$var wire 1 2 auto_load $end
$var wire 1 " clk_in $end
$var wire 1 0 en $end
$var wire 1 / go $end
$var wire 3 6 prescaler_conf [2:0] $end
$var wire 1 & rst $end
$var wire 16 7 timer_conf [15:0] $end
$var wire 1 ) write $end
$var reg 1 . go_clear $end
$var reg 7 8 prescaler_out [6:0] $end
$var reg 1 9 selected_freq $end
$var reg 16 : timer_count [15:0] $end
$var reg 2 ; timer_state [1:0] $end
$var reg 1 + tmr_int $end
$upscope $end
$upscope $end
$upscope $end
$scope module timer_tb $end
$var wire 8 < config_in [7:0] $end
$upscope $end
$scope module timer_tb $end
$var wire 8 = config_out [7:0] $end
$upscope $end
$scope module timer_tb $end
$var wire 1 > interrupt $end
$upscope $end
$enddefinitions $end
#0
$dumpvars
x>
bx =
b0 <
bx ;
bx :
09
bx 8
b1111111111110000 7
bx 6
x5
bx 4
x3
x2
bx 1
x0
x/
x.
bx -
bx ,
x+
0*
0)
x(
b1111111111110000 '
0&
0%
x$
b0 #
0"
b1 !
$end
#2000
b0 ;
19
1"
#4000
09
0"
#6000
19
1"
#8000
09
0"
#10000
0$
b0 -
0(
0/
00
02
b0 ,
b0 6
0>
0.
0+
b0 :
b0 8
05
03
b0 1
b0 4
b0 =
19
1"
1&
#12000
09
0"
#14000
19
1"
#16000
09
0"
#18000
19
1"
#20000
09
0"
0&
#22000
b1 8
19
1"
#24000
09
0"
#26000
b10 8
19
1"
#28000
09
0"
#30000
b11 8
19
1"
b110000 #
b110000 <
#32000
09
0"
#34000
b100 8
19
1"
#36000
09
0"
#38000
b101 8
19
1"
#40000
09
0"
#42000
b110 8
19
1"
#44000
09
0"
#46000
b111 8
19
1"
#48000
09
0"
#50000
b1000 8
19
1"
#52000
09
0"
#54000
b1001 8
19
1"
#56000
09
0"
#58000
b1010 8
19
1"
#60000
09
0"
#62000
b1011 8
19
1"
#64000
09
0"
#66000
b1100 8
19
1"
#68000
09
0"
#70000
b1101 8
19
1"
#72000
09
0"
#74000
b1110 8
19
1"
#76000
09
0"
#78000
b1111 8
19
1"
#80000
09
0"
b110100 #
b110100 <
#82000
b10000 8
19
1"
#84000
09
0"
#86000
b10001 8
19
1"
#88000
09
0"
#90000
b10010 8
19
1"
b110110 #
b110110 <
#92000
09
0"
#94000
b10011 8
19
1"
#96000
09
0"
#98000
b10100 8
19
1"
#100000
1*
09
0"
1)
#102000
1/
10
b11 ,
b11 6
b110110 1
b110110 4
b110110 =
b0 8
09
1"
#104000
0"
#106000
1"
#108000
0"
#110000
b1 8
0*
1"
0)
#112000
0"
#114000
b10 8
1"
#116000
0"
#118000
b11 8
1"
#120000
0"
#122000
b1 ;
b1111111111110000 :
19
b100 8
1"
#124000
0"
#126000
b101 8
1"
#128000
0"
#130000
b110 8
1"
#132000
0"
#134000
b111 8
1"
#136000
0"
#138000
09
b1000 8
1"
#140000
0"
#142000
b1001 8
1"
#144000
0"
#146000
b1010 8
1"
#148000
0"
#150000
b1011 8
1"
#152000
0"
#154000
b1111111111110001 :
19
b1100 8
1"
#156000
0"
#158000
b1101 8
1"
#160000
0"
#162000
b1110 8
1"
#164000
0"
#166000
b1111 8
1"
#168000
0"
#170000
09
b10000 8
1"
#172000
0"
#174000
b10001 8
1"
#176000
0"
#178000
b10010 8
1"
#180000
0"
#182000
b10011 8
1"
#184000
0"
#186000
b1111111111110010 :
19
b10100 8
1"
#188000
0"
#190000
b10101 8
1"
#192000
0"
#194000
b10110 8
1"
#196000
0"
#198000
b10111 8
1"
#200000
0"
#202000
09
b11000 8
1"
#204000
0"
#206000
b11001 8
1"
#208000
0"
#210000
b11010 8
1"
#212000
0"
#214000
b11011 8
1"
#216000
0"
#218000
b1111111111110011 :
19
b11100 8
1"
#220000
0"
#222000
b11101 8
1"
#224000
0"
#226000
b11110 8
1"
#228000
0"
#230000
b11111 8
1"
#232000
0"
#234000
09
b100000 8
1"
#236000
0"
#238000
b100001 8
1"
#240000
0"
#242000
b100010 8
1"
#244000
0"
#246000
b100011 8
1"
#248000
0"
#250000
b1111111111110100 :
19
b100100 8
1"
#252000
0"
#254000
b100101 8
1"
#256000
0"
#258000
b100110 8
1"
#260000
0"
#262000
b100111 8
1"
#264000
0"
#266000
09
b101000 8
1"
#268000
0"
#270000
b101001 8
1"
#272000
0"
#274000
b101010 8
1"
#276000
0"
#278000
b101011 8
1"
#280000
0"
#282000
b1111111111110101 :
19
b101100 8
1"
#284000
0"
#286000
b101101 8
1"
#288000
0"
#290000
b101110 8
1"
#292000
0"
#294000
b101111 8
1"
#296000
0"
#298000
09
b110000 8
1"
#300000
0"
#302000
b110001 8
1"
#304000
0"
#306000
b110010 8
1"
#308000
0"
#310000
b110011 8
1"
#312000
0"
#314000
b1111111111110110 :
19
b110100 8
1"
#316000
0"
#318000
b110101 8
1"
#320000
0"
#322000
b110110 8
1"
#324000
0"
#326000
b110111 8
1"
#328000
0"
#330000
09
b111000 8
1"
#332000
0"
#334000
b111001 8
1"
#336000
0"
#338000
b111010 8
1"
#340000
0"
#342000
b111011 8
1"
#344000
0"
#346000
b1111111111110111 :
19
b111100 8
1"
#348000
0"
#350000
b111101 8
1"
#352000
0"
#354000
b111110 8
1"
#356000
0"
#358000
b111111 8
1"
#360000
0"
#362000
09
b1000000 8
1"
#364000
0"
#366000
b1000001 8
1"
#368000
0"
#370000
b1000010 8
1"
#372000
0"
#374000
b1000011 8
1"
#376000
0"
#378000
b1111111111111000 :
19
b1000100 8
1"
#380000
1*
0"
1)
#382000
09
b0 8
1"
#384000
0"
#386000
1"
#388000
0"
#390000
b1 8
0*
1"
0)
#392000
0"
#394000
b10 8
1"
#396000
0"
#398000
b11 8
1"
#400000
0"
#402000
b1111111111111001 :
19
b100 8
1"
#404000
0"
#406000
b101 8
1"
#408000
0"
#410000
b110 8
1"
#412000
0"
#414000
b111 8
1"
#416000
0"
#418000
09
b1000 8
1"
#420000
0"
#422000
b1001 8
1"
#424000
0"
#426000
b1010 8
1"
#428000
0"
#430000
b1011 8
1"
#432000
0"
#434000
b1111111111111010 :
19
b1100 8
1"
#436000
0"
#438000
b1101 8
1"
#440000
0"
#442000
b1110 8
1"
#444000
0"
#446000
b1111 8
1"
#448000
0"
#450000
09
b10000 8
1"
#452000
0"
#454000
b10001 8
1"
#456000
0"
#458000
b10010 8
1"
#460000
0"
#462000
b10011 8
1"
#464000
0"
#466000
b1111111111111011 :
19
b10100 8
1"
#468000
0"
#470000
b10101 8
1"
#472000
0"
#474000
b10110 8
1"
#476000
0"
#478000
b10111 8
1"
#480000
0"
#482000
09
b11000 8
1"
#484000
0"
#486000
b11001 8
1"
#488000
0"
#490000
b11010 8
1"
#492000
0"
#494000
b11011 8
1"
#496000
0"
#498000
b1111111111111100 :
19
b11100 8
1"
#500000
0"
#502000
b11101 8
1"
#504000
0"
#506000
b11110 8
1"
#508000
0"
#510000
b11111 8
1"
#512000
0"
#514000
09
b100000 8
1"
#516000
0"
#518000
b100001 8
1"
#520000
0"
#522000
b100010 8
1"
#524000
0"
#526000
b100011 8
1"
#528000
0"
#530000
b1111111111111101 :
19
b100100 8
1"
#532000
0"
#534000
b100101 8
1"
#536000
0"
#538000
b100110 8
1"
#540000
0"
#542000
b100111 8
1"
#544000
0"
#546000
09
b101000 8
1"
#548000
0"
#550000
b101001 8
1"
#552000
0"
#554000
b101010 8
1"
#556000
0"
#558000
b101011 8
1"
#560000
0"
#562000
b1111111111111110 :
19
b101100 8
1"
#564000
0"
#566000
b101101 8
1"
#568000
0"
#570000
b101110 8
1"
#572000
0"
#574000
b101111 8
1"
#576000
0"
#578000
09
b110000 8
1"
#580000
0"
#582000
b110001 8
1"
#584000
0"
#586000
b110010 8
1"
#588000
0"
#590000
b110011 8
1"
#592000
0"
#594000
b1111111111111111 :
19
b110100 8
1"
#596000
0"
#598000
b110101 8
1"
#600000
0"
#602000
b110110 8
1"
#604000
0"
#606000
b110111 8
1"
#608000
0"
#610000
09
b111000 8
1"
#612000
0"
#614000
b111001 8
1"
#616000
0"
#618000
b111010 8
1"
#620000
0"
#622000
b111011 8
1"
#624000
0"
#626000
b10 -
1$
1.
b11 ;
b0 :
19
b111100 8
1"
#628000
0"
#630000
b0 -
0$
0/
b110100 1
b110100 4
b110100 =
13
b111101 8
1"
#632000
0"
#634000
b111110 8
1"
#636000
0"
#638000
b111111 8
1"
#640000
0"
#642000
09
b1000000 8
1"
#644000
0"
#646000
b1000001 8
1"
#648000
0"
#650000
b1000010 8
1"
#652000
0"
#654000
b1000011 8
1"
#656000
0"
#658000
b1 -
1(
b0 ;
0.
1+
19
b1000100 8
1"
#660000
0"
#662000
b0 -
0(
1>
b110101 1
b110101 4
b110101 =
15
03
b1000101 8
1"
#664000
0"
#666000
b1000110 8
1"
#668000
0"
#670000
b1000111 8
1"
#672000
0"
#674000
09
b1001000 8
1"
#676000
0"
#678000
b1001001 8
1"
#680000
0"
#682000
b1001010 8
1"
#684000
0"
#686000
b1001011 8
1"
#688000
0"
#690000
0+
19
b1001100 8
1"
b111110 #
b111110 <
#692000
0"
#694000
05
b1001101 8
1"
#696000
0"
#698000
b1001110 8
1"
#700000
1*
0"
1)
#702000
1/
12
0>
09
b111110 1
b111110 4
b111110 =
b0 8
1"
#704000
0"
#706000
1"
#708000
0"
#710000
b1 8
0*
1"
0)
#712000
0"
#714000
b10 8
1"
#716000
0"
#718000
b11 8
1"
#720000
0"
#722000
b1 ;
b1111111111110000 :
19
b100 8
1"
#724000
0"
#726000
b101 8
1"
#728000
0"
#730000
b110 8
1"
#732000
0"
#734000
b111 8
1"
#736000
0"
#738000
09
b1000 8
1"
#740000
0"
#742000
b1001 8
1"
#744000
0"
#746000
b1010 8
1"
#748000
0"
#750000
b1011 8
1"
#752000
0"
#754000
b1111111111110001 :
19
b1100 8
1"
#756000
0"
#758000
b1101 8
1"
#760000
0"
#762000
b1110 8
1"
#764000
0"
#766000
b1111 8
1"
#768000
0"
#770000
09
b10000 8
1"
#772000
0"
#774000
b10001 8
1"
#776000
0"
#778000
b10010 8
1"
#780000
0"
#782000
b10011 8
1"
#784000
0"
#786000
b1111111111110010 :
19
b10100 8
1"
#788000
0"
#790000
b10101 8
1"
#792000
0"
#794000
b10110 8
1"
#796000
0"
#798000
b10111 8
1"
#800000
0"
#802000
09
b11000 8
1"
#804000
0"
#806000
b11001 8
1"
#808000
0"
#810000
b11010 8
1"
#812000
0"
#814000
b11011 8
1"
#816000
0"
#818000
b1111111111110011 :
19
b11100 8
1"
#820000
0"
#822000
b11101 8
1"
#824000
0"
#826000
b11110 8
1"
#828000
0"
#830000
b11111 8
1"
#832000
0"
#834000
09
b100000 8
1"
#836000
0"
#838000
b100001 8
1"
#840000
0"
#842000
b100010 8
1"
#844000
0"
#846000
b100011 8
1"
#848000
0"
#850000
b1111111111110100 :
19
b100100 8
1"
#852000
0"
#854000
b100101 8
1"
#856000
0"
#858000
b100110 8
1"
#860000
0"
#862000
b100111 8
1"
#864000
0"
#866000
09
b101000 8
1"
#868000
0"
#870000
b101001 8
1"
#872000
0"
#874000
b101010 8
1"
#876000
0"
#878000
b101011 8
1"
#880000
0"
#882000
b1111111111110101 :
19
b101100 8
1"
#884000
0"
#886000
b101101 8
1"
#888000
0"
#890000
b101110 8
1"
#892000
0"
#894000
b101111 8
1"
#896000
0"
#898000
09
b110000 8
1"
#900000
0"
#902000
b110001 8
1"
#904000
0"
#906000
b110010 8
1"
#908000
0"
#910000
b110011 8
1"
#912000
0"
#914000
b1111111111110110 :
19
b110100 8
1"
#916000
0"
#918000
b110101 8
1"
#920000
0"
#922000
b110110 8
1"
#924000
0"
#926000
b110111 8
1"
#928000
0"
#930000
09
b111000 8
1"
#932000
0"
#934000
b111001 8
1"
#936000
0"
#938000
b111010 8
1"
#940000
0"
#942000
b111011 8
1"
#944000
0"
#946000
b1111111111110111 :
19
b111100 8
1"
#948000
0"
#950000
b111101 8
1"
#952000
0"
#954000
b111110 8
1"
#956000
0"
#958000
b111111 8
1"
#960000
0"
#962000
09
b1000000 8
1"
#964000
0"
#966000
b1000001 8
1"
#968000
0"
#970000
b1000010 8
1"
#972000
0"
#974000
b1000011 8
1"
#976000
0"
#978000
b1111111111111000 :
19
b1000100 8
1"
#980000
0"
b111100 #
b111100 <
#982000
b1000101 8
1"
#984000
0"
#986000
b1000110 8
1"
#988000
0"
#990000
09
b0 8
1*
1"
1)
#992000
0"
#994000
0/
b111100 1
b111100 4
b111100 =
1"
#996000
0"
#998000
1"
#1000000
0*
0"
0)
#1002000
b1 8
1"
#1004000
0"
#1006000
b10 8
1"
#1008000
0"
#1010000
b11 8
1"
#1012000
0"
#1014000
b1111111111111001 :
19
b100 8
1"
#1016000
0"
#1018000
b101 8
1"
#1020000
0"
#1022000
b110 8
1"
#1024000
0"
#1026000
b111 8
1"
#1028000
0"
#1030000
09
b1000 8
1"
#1032000
0"
#1034000
b1001 8
1"
#1036000
0"
#1038000
b1010 8
1"
#1040000
0"
#1042000
b1011 8
1"
#1044000
0"
#1046000
b1111111111111010 :
19
b1100 8
1"
#1048000
0"
#1050000
b1101 8
1"
#1052000
0"
#1054000
b1110 8
1"
#1056000
0"
#1058000
b1111 8
1"
#1060000
0"
#1062000
09
b10000 8
1"
#1064000
0"
#1066000
b10001 8
1"
#1068000
0"
#1070000
b10010 8
1"
#1072000
0"
#1074000
b10011 8
1"
#1076000
0"
#1078000
b1111111111111011 :
19
b10100 8
1"
#1080000
0"
#1082000
b10101 8
1"
#1084000
0"
#1086000
b10110 8
1"
#1088000
0"
#1090000
b10111 8
1"
#1092000
0"
#1094000
09
b11000 8
1"
#1096000
0"
#1098000
b11001 8
1"
#1100000
0"
#1102000
b11010 8
1"
#1104000
0"
#1106000
b11011 8
1"
#1108000
0"
#1110000
b1111111111111100 :
19
b11100 8
1"
#1112000
0"
#1114000
b11101 8
1"
#1116000
0"
#1118000
b11110 8
1"
#1120000
0"
#1122000
b11111 8
1"
#1124000
0"
#1126000
09
b100000 8
1"
#1128000
0"
#1130000
b100001 8
1"
#1132000
0"
#1134000
b100010 8
1"
#1136000
0"
#1138000
b100011 8
1"
#1140000
0"
#1142000
b1111111111111101 :
19
b100100 8
1"
#1144000
0"
#1146000
b100101 8
1"
#1148000
0"
#1150000
b100110 8
1"
#1152000
0"
#1154000
b100111 8
1"
#1156000
0"
#1158000
09
b101000 8
1"
#1160000
0"
#1162000
b101001 8
1"
#1164000
0"
#1166000
b101010 8
1"
#1168000
0"
#1170000
b101011 8
1"
#1172000
0"
#1174000
b1111111111111110 :
19
b101100 8
1"
#1176000
0"
#1178000
b101101 8
1"
#1180000
0"
#1182000
b101110 8
1"
#1184000
0"
#1186000
b101111 8
1"
#1188000
0"
#1190000
09
b110000 8
1"
#1192000
0"
#1194000
b110001 8
1"
#1196000
0"
#1198000
b110010 8
1"
#1200000
0"
#1202000
b110011 8
1"
#1204000
0"
#1206000
b1111111111111111 :
19
b110100 8
1"
#1208000
0"
#1210000
b110101 8
1"
#1212000
0"
#1214000
b110110 8
1"
#1216000
0"
#1218000
b110111 8
1"
#1220000
0"
#1222000
09
b111000 8
1"
#1224000
0"
#1226000
b111001 8
1"
#1228000
0"
#1230000
b111010 8
1"
#1232000
0"
#1234000
b111011 8
1"
#1236000
0"
#1238000
b10 -
1$
1.
b11 ;
b0 :
19
b111100 8
1"
#1240000
0"
#1242000
b0 -
0$
b111101 8
13
1"
#1244000
0"
#1246000
b111110 8
1"
#1248000
0"
#1250000
b111111 8
1"
#1252000
0"
#1254000
09
b1000000 8
1"
#1256000
0"
#1258000
b1000001 8
1"
#1260000
0"
#1262000
b1000010 8
1"
#1264000
0"
#1266000
b1000011 8
1"
#1268000
0"
#1270000
b1 -
1(
b1 ;
b1111111111110000 :
0.
1+
19
b1000100 8
1"
b110100 #
b110100 <
#1272000
0"
#1274000
b0 -
0(
1>
b1000101 8
15
03
b111101 1
b111101 4
b111101 =
1"
#1276000
0"
#1278000
b1000110 8
1"
#1280000
1*
0"
1)
#1282000
09
02
0>
b0 8
b110100 1
b110100 4
b110100 =
1"
#1284000
0"
#1286000
1"
#1288000
0"
#1290000
b1 8
0*
1"
0)
#1292000
0"
#1294000
b10 8
1"
#1296000
0"
#1298000
b11 8
1"
#1300000
0"
#1302000
0+
b1111111111110001 :
19
b100 8
1"
#1304000
0"
#1306000
b101 8
05
1"
#1308000
0"
#1310000
b110 8
1"
#1312000
0"
#1314000
b111 8
1"
#1316000
0"
#1318000
09
b1000 8
1"
#1320000
0"
#1322000
b1001 8
1"
#1324000
0"
#1326000
b1010 8
1"
#1328000
0"
#1330000
b1011 8
1"
#1332000
0"
#1334000
b1111111111110010 :
19
b1100 8
1"
#1336000
0"
#1338000
b1101 8
1"
#1340000
0"
#1342000
b1110 8
1"
#1344000
0"
#1346000
b1111 8
1"
#1348000
0"
#1350000
09
b10000 8
1"
#1352000
0"
#1354000
b10001 8
1"
#1356000
0"
#1358000
b10010 8
1"
#1360000
0"
#1362000
b10011 8
1"
#1364000
0"
#1366000
b1111111111110011 :
19
b10100 8
1"
#1368000
0"
#1370000
b10101 8
1"
#1372000
0"
#1374000
b10110 8
1"
#1376000
0"
#1378000
b10111 8
1"
#1380000
0"
#1382000
09
b11000 8
1"
#1384000
0"
#1386000
b11001 8
1"
#1388000
0"
#1390000
b11010 8
1"
#1392000
0"
#1394000
b11011 8
1"
#1396000
0"
#1398000
b1111111111110100 :
19
b11100 8
1"
#1400000
0"
#1402000
b11101 8
1"
#1404000
0"
#1406000
b11110 8
1"
#1408000
0"
#1410000
b11111 8
1"
#1412000
0"
#1414000
09
b100000 8
1"
#1416000
0"
#1418000
b100001 8
1"
#1420000
0"
#1422000
b100010 8
1"
#1424000
0"
#1426000
b100011 8
1"
#1428000
0"
#1430000
b1111111111110101 :
19
b100100 8
1"
#1432000
0"
#1434000
b100101 8
1"
#1436000
0"
#1438000
b100110 8
1"
#1440000
0"
#1442000
b100111 8
1"
#1444000
0"
#1446000
09
b101000 8
1"
#1448000
0"
#1450000
b101001 8
1"
#1452000
0"
#1454000
b101010 8
1"
#1456000
0"
#1458000
b101011 8
1"
#1460000
0"
#1462000
b1111111111110110 :
19
b101100 8
1"
#1464000
0"
#1466000
b101101 8
1"
#1468000
0"
#1470000
b101110 8
1"
#1472000
0"
#1474000
b101111 8
1"
#1476000
0"
#1478000
09
b110000 8
1"
#1480000
0"
#1482000
b110001 8
1"
#1484000
0"
#1486000
b110010 8
1"
#1488000
0"
#1490000
b110011 8
1"
#1492000
0"
#1494000
b1111111111110111 :
19
b110100 8
1"
#1496000
0"
#1498000
b110101 8
1"
#1500000
0"
#1502000
b110110 8
1"
#1504000
0"
#1506000
b110111 8
1"
#1508000
0"
#1510000
09
b111000 8
1"
#1512000
0"
#1514000
b111001 8
1"
#1516000
0"
#1518000
b111010 8
1"
#1520000
0"
#1522000
b111011 8
1"
#1524000
0"
#1526000
b1111111111111000 :
19
b111100 8
1"
#1528000
0"
#1530000
b111101 8
1"
#1532000
0"
#1534000
b111110 8
1"
#1536000
0"
#1538000
b111111 8
1"
#1540000
0"
#1542000
09
b1000000 8
1"
#1544000
0"
#1546000
b1000001 8
1"
#1548000
0"
#1550000
b1000010 8
1"
#1552000
0"
#1554000
b1000011 8
1"
#1556000
0"
#1558000
b1111111111111001 :
19
b1000100 8
1"
#1560000
0"
b111100 #
b111100 <
#1562000
b1000101 8
1"
#1564000
0"
#1566000
b1000110 8
1"
#1568000
0"
#1570000
09
b0 8
1*
1"
1)
#1572000
0"
#1574000
12
b111100 1
b111100 4
b111100 =
1"
#1576000
0"
#1578000
1"
#1580000
0*
0"
0)
#1582000
b1 8
1"
#1584000
0"
#1586000
b10 8
1"
#1588000
0"
#1590000
b11 8
1"
#1592000
0"
#1594000
b1111111111111010 :
19
b100 8
1"
#1596000
0"
#1598000
b101 8
1"
#1600000
0"
#1602000
b110 8
1"
#1604000
0"
#1606000
b111 8
1"
#1608000
0"
#1610000
09
b1000 8
1"
#1612000
0"
#1614000
b1001 8
1"
#1616000
0"
#1618000
b1010 8
1"
#1620000
0"
#1622000
b1011 8
1"
#1624000
0"
#1626000
b1111111111111011 :
19
b1100 8
1"
#1628000
0"
#1630000
b1101 8
1"
#1632000
0"
#1634000
b1110 8
1"
#1636000
0"
#1638000
b1111 8
1"
#1640000
0"
#1642000
09
b10000 8
1"
#1644000
0"
#1646000
b10001 8
1"
#1648000
0"
#1650000
b10010 8
1"
#1652000
0"
#1654000
b10011 8
1"
#1656000
0"
#1658000
b1111111111111100 :
19
b10100 8
1"
#1660000
0"
#1662000
b10101 8
1"
#1664000
0"
#1666000
b10110 8
1"
#1668000
0"
#1670000
b10111 8
1"
#1672000
0"
#1674000
09
b11000 8
1"
#1676000
0"
#1678000
b11001 8
1"
#1680000
0"
#1682000
b11010 8
1"
#1684000
0"
#1686000
b11011 8
1"
#1688000
0"
#1690000
b1111111111111101 :
19
b11100 8
1"
#1692000
0"
#1694000
b11101 8
1"
#1696000
0"
#1698000
b11110 8
1"
#1700000
0"
#1702000
b11111 8
1"
#1704000
0"
#1706000
09
b100000 8
1"
#1708000
0"
#1710000
b100001 8
1"
#1712000
0"
#1714000
b100010 8
1"
#1716000
0"
#1718000
b100011 8
1"
#1720000
0"
#1722000
b1111111111111110 :
19
b100100 8
1"
#1724000
0"
#1726000
b100101 8
1"
#1728000
0"
#1730000
b100110 8
1"
#1732000
0"
#1734000
b100111 8
1"
#1736000
0"
#1738000
09
b101000 8
1"
#1740000
0"
#1742000
b101001 8
1"
#1744000
0"
#1746000
b101010 8
1"
#1748000
0"
#1750000
b101011 8
1"
#1752000
0"
#1754000
b1111111111111111 :
19
b101100 8
1"
#1756000
0"
#1758000
b101101 8
1"
#1760000
0"
#1762000
b101110 8
1"
#1764000
0"
#1766000
b101111 8
1"
#1768000
0"
#1770000
09
b110000 8
1"
#1772000
0"
#1774000
b110001 8
1"
#1776000
0"
