pacoblaze/bamse_v1/iverilog/timer/timer.v
`ifndef TIMER_V
`define TIMER_V

module timer(
	clk_in,
	rst,
	prescaler_conf,
	timer_conf,
	en,
	go,
	auto_load,
	tmr_int,
	go_clear,
	address,
	ren,	
);

input clk_in;
input rst; //(H)
input [2:0] prescaler_conf; //Select between 8 possible frequencies 000 -> clk_in : 111 -> clk_in/128
input [15:0] timer_conf; // 16 bit load value for the counter 
input en; //enable (H)
input go; //start (H)
input auto_load; //automatic restart timer after rolloff (H)
output reg tmr_int; //interrupt (H)
output reg go_clear;
input [7:0] address;
input ren;

parameter ADDR = 8'b0000_0000; 

reg [6:0] prescaler_out;

//Prescaler
reg prescaler_reset;

always @(posedge clk_in) begin
	if (rst) begin
		prescaler_out <= 0;		
	end else begin
		if (en) begin
			if (prescaler_reset) begin
				prescaler_out <= 0;
			end else begin
				prescaler_out <= prescaler_out + 1;
			end		
		end
	end
end

//Prescaler selector

reg selected_freq;

always @(*) begin
	case (prescaler_conf)
		3'b000: selected_freq = clk_in;
		3'b001: selected_freq = prescaler_out[0];
		3'b010: selected_freq = prescaler_out[1];
		3'b011: selected_freq = prescaler_out[2];
		3'b100: selected_freq = prescaler_out[3];
		3'b101: selected_freq = prescaler_out[4]; 
		3'b110: selected_freq = prescaler_out[5];
		3'b111: selected_freq = prescaler_out[6];
	endcase
end

//Timer
reg [15:0] timer_count;
reg [1:0] timer_state;

parameter IDLE  = 2'b00, 
		  GO =    2'b01,
		  ROLL  = 2'b11,
		  WAIT  = 2'b10;


wire read_flag;
assign read_flag = (address == ADDR && ren)? 1'b1 : 1'b0;

always @(posedge selected_freq) begin
	if (rst) begin
		timer_count <= 0;					
		tmr_int <= 0;
		timer_state <= IDLE;
		prescaler_reset <= 0;
		go_clear <= 0;
	end else begin 
		if (en) begin
			case (timer_state)
				IDLE:	begin
							if (go) begin 
								timer_count <= timer_conf;														
								timer_state <= GO;
								prescaler_reset <= 1;
							end 
							
							if (read_flag) tmr_int <= 0;
						
						end
				GO:		begin 
							prescaler_reset <= 0;
							timer_count <= timer_count + 1;
							
							if (timer_count == 16'hffff) begin
								timer_state <= ROLL;
								go_clear <= 1;
							end							
							
							if (read_flag) tmr_int <= 0;													
						end
				ROLL: 	begin
							tmr_int <= 1;
							go_clear <= 0;
							if (auto_load) begin
								timer_count <= timer_conf;														
								timer_state <= GO;
							end else begin
								timer_state <= IDLE;
							end
						end				
			endcase
		end else begin
			timer_state <= IDLE;
		end
	
	end
end

endmodule

`endif

pacoblaze/bamse_v1/iverilog/timer/timer_tb.v
//timer_tb.v

`timescale 1ns/1ps

`include "timer.v"

module timer_tb();

reg clk_in;
reg rst;
reg [2:0] prescaler_conf;
reg [15:0] timer_conf; 
reg en; //enable (H)
reg go; //start (H)
reg auto_load; //automatic restart timer after rolloff (H)
wire tmr_int; //interrupt (H)
wire go_clear;
reg [7:0] address;
reg ren;
reg wen;


reg go_aux;

parameter ADDR=8'h00

//Resetable register
always @(posedge clk_in) begin
	if (rst) begin
		go_aux <= 0;
	end else if (go_clear) begin
		go_aux <= ~go_clear & go_aux;
	end	else if (address == (ADDR && wen)) begin
		go_aux <= go;	
	end
end


timer #(.ADDR(8'h00)) dut(
	.clk_in(clk_in),
	.rst(rst),
	.prescaler_conf(prescaler_conf),
	.timer_conf(timer_conf),
	.en(en),
	.go(go_aux),
	.auto_load(auto_load),
	.tmr_int(tmr_int),
	.address(address),
	.ren(ren),
	.go_clear(go_clear)
);

always #(2) clk_in = ~clk_in;

initial begin
	$dumpfile("dump.vcd");
	$dumpvars(0,dut,go,go_aux);
	
	clk_in = 0;
	rst = 0;
	prescaler_conf = 0;
	timer_conf = 16'hfff0;
	en = 0;
	go = 0;
	auto_load = 0;
	address = 8'h00;
	ren = 0;
	
	#10 rst = 1;
	#10 rst = 0;
	#50 en = 1;
	#10 go = 1;
	#10 go = 0;
	
		
	#100 rst = 1;
	#10 rst = 0;
	#10 auto_load = 1;
	#10 go = 1;
	#10 go = 0;	
	
	#100 ren = 1;
	#10 ren = 0;
	
	#100 ren = 1;
	#10 ren = 0;
	
	#200 
	#(250) $finish;
end

endmodule

pacoblaze/bamse_v1/iverilog/timer/dump.vcd
$date
	Wed Oct  2 23:41:39 2019
$end
$version
	Icarus Verilog
$end
$timescale
	1ps
$end
$scope module timer_tb $end
$scope module dut $end
$var wire 8 ! address [7:0] $end
$var wire 1 " auto_load $end
$var wire 1 # clk_in $end
$var wire 1 $ en $end
$var wire 1 % go $end
$var wire 3 & prescaler_conf [2:0] $end
$var wire 1 ' ren $end
$var wire 1 ( rst $end
$var wire 16 ) timer_conf [15:0] $end
$var wire 1 * read_flag $end
$var reg 1 + go_clear $end
$var reg 7 , prescaler_out [6:0] $end
$var reg 1 - prescaler_reset $end
$var reg 1 . selected_freq $end
$var reg 16 / timer_count [15:0] $end
$var reg 2 0 timer_state [1:0] $end
$var reg 1 1 tmr_int $end
$upscope $end
$upscope $end
$scope module timer_tb $end
$var reg 1 2 go $end
$upscope $end
$scope module timer_tb $end
$var reg 1 % go_aux $end
$upscope $end
$enddefinitions $end
#0
$dumpvars
02
x1
bx 0
bx /
0.
x-
bx ,
x+
0*
b1111111111110000 )
0(
0'
b0 &
x%
0$
0#
0"
b0 !
$end
#2000
b0 0
1.
1#
#4000
0.
0#
#6000
1.
1#
#8000
0.
0#
#10000
0+
0-
01
b0 /
b0 ,
0%
1.
1#
1(
#12000
0.
0#
#14000
1.
1#
#16000
0.
0#
#18000
1.
1#
#20000
0.
0#
0(
#22000
1.
1#
#24000
0.
0#
#26000
1.
1#
#28000
0.
0#
#30000
1.
1#
#32000
0.
0#
#34000
1.
1#
#36000
0.
0#
#38000
1.
1#
#40000
0.
0#
#42000
1.
1#
#44000
0.
0#
#46000
1.
1#
#48000
0.
0#
#50000
1.
1#
#52000
0.
0#
#54000
1.
1#
#56000
0.
0#
#58000
1.
1#
#60000
0.
0#
#62000
1.
1#
#64000
0.
0#
#66000
1.
1#
#68000
0.
0#
#70000
b1 ,
1.
1#
1$
#72000
0.
0#
#74000
b10 ,
1.
1#
#76000
0.
0#
#78000
b11 ,
1.
1#
#80000
0.
0#
12
#82000
b100 ,
1%
1.
1#
#84000
0.
0#
#86000
1-
b1 0
b1111111111110000 /
b101 ,
1.
1#
#88000
0.
0#
#90000
b1111111111110001 /
0-
b0 ,
1.
1#
02
#92000
0.
0#
#94000
b1111111111110010 /
b1 ,
1.
1#
#96000
0.
0#
#98000
b1111111111110011 /
b10 ,
1.
1#
#100000
0.
0#
#102000
b1111111111110100 /
b11 ,
1.
1#
#104000
0.
0#
#106000
b1111111111110101 /
b100 ,
1.
1#
#108000
0.
0#
#110000
b1111111111110110 /
b101 ,
1.
1#
#112000
0.
0#
#114000
b1111111111110111 /
b110 ,
1.
1#
#116000
0.
0#
#118000
b1111111111111000 /
b111 ,
1.
1#
#120000
0.
0#
#122000
b1111111111111001 /
b1000 ,
1.
1#
#124000
0.
0#
#126000
b1111111111111010 /
b1001 ,
1.
1#
#128000
0.
0#
#130000
b1111111111111011 /
b1010 ,
1.
1#
#132000
0.
0#
#134000
b1111111111111100 /
b1011 ,
1.
1#
#136000
0.
0#
#138000
b1111111111111101 /
b1100 ,
1.
1#
#140000
0.
0#
#142000
b1111111111111110 /
b1101 ,
1.
1#
#144000
0.
0#
#146000
b1111111111111111 /
b1110 ,
1.
1#
#148000
0.
0#
#150000
1+
b11 0
b0 /
b1111 ,
1.
1#
#152000
0.
0#
#154000
b0 0
0+
11
b10000 ,
0%
1.
1#
#156000
0.
0#
#158000
b10001 ,
1.
1#
#160000
0.
0#
#162000
b10010 ,
1.
1#
#164000
0.
0#
#166000
b10011 ,
1.
1#
#168000
0.
0#
#170000
b10100 ,
1.
1#
#172000
0.
0#
#174000
b10101 ,
1.
1#
#176000
0.
0#
#178000
b10110 ,
1.
1#
#180000
0.
0#
#182000
b10111 ,
1.
1#
#184000
0.
0#
#186000
b11000 ,
1.
1#
#188000
0.
0#
#190000
01
b0 ,
1.
1#
1(
#192000
0.
0#
#194000
1.
1#
#196000
0.
0#
#198000
1.
1#
#200000
0.
0#
0(
#202000
b1 ,
1.
1#
#204000
0.
0#
#206000
b10 ,
1.
1#
#208000
0.
0#
#210000
b11 ,
1.
1#
1"
#212000
0.
0#
#214000
b100 ,
1.
1#
#216000
0.
0#
#218000
b101 ,
1.
1#
#220000
0.
0#
12
#222000
1%
b110 ,
1.
1#
#224000
0.
0#
#226000
1-
b1 0
b1111111111110000 /
b111 ,
1.
1#
#228000
0.
0#
#230000
b1111111111110001 /
0-
b0 ,
1.
1#
02
#232000
0.
0#
#234000
b1111111111110010 /
b1 ,
1.
1#
#236000
0.
0#
#238000
b1111111111110011 /
b10 ,
1.
1#
#240000
0.
0#
#242000
b1111111111110100 /
b11 ,
1.
1#
#244000
0.
0#
#246000
b1111111111110101 /
b100 ,
1.
1#
#248000
0.
0#
#250000
b1111111111110110 /
b101 ,
1.
1#
#252000
0.
0#
#254000
b1111111111110111 /
b110 ,
1.
1#
#256000
0.
0#
#258000
b1111111111111000 /
b111 ,
1.
1#
#260000
0.
0#
#262000
b1111111111111001 /
b1000 ,
1.
1#
#264000
0.
0#
#266000
b1111111111111010 /
b1001 ,
1.
1#
#268000
0.
0#
#270000
b1111111111111011 /
b1010 ,
1.
1#
#272000
0.
0#
#274000
b1111111111111100 /
b1011 ,
1.
1#
#276000
0.
0#
#278000
b1111111111111101 /
b1100 ,
1.
1#
#280000
0.
0#
#282000
b1111111111111110 /
b1101 ,
1.
1#
#284000
0.
0#
#286000
b1111111111111111 /
b1110 ,
1.
1#
#288000
0.
0#
#290000
1+
b11 0
b0 /
b1111 ,
1.
1#
#292000
0.
0#
#294000
b1 0
b1111111111110000 /
0+
11
0%
b10000 ,
1.
1#
#296000
0.
0#
#298000
b1111111111110001 /
b10001 ,
1.
1#
#300000
0.
0#
#302000
b1111111111110010 /
b10010 ,
1.
1#
#304000
0.
0#
#306000
b1111111111110011 /
b10011 ,
1.
1#
#308000
0.
0#
#310000
b1111111111110100 /
b10100 ,
1.
1#
#312000
0.
0#
#314000
b1111111111110101 /
b10101 ,
1.
1#
#316000
0.
0#
#318000
b1111111111110110 /
b10110 ,
1.
1#
#320000
0.
0#
#322000
b1111111111110111 /
b10111 ,
1.
1#
#324000
0.
0#
#326000
b1111111111111000 /
b11000 ,
1.
1#
#328000
0.
0#
#330000
01
b1111111111111001 /
b11001 ,
1*
1.
1#
1'
#332000
0.
0#
#334000
b1111111111111010 /
b11010 ,
1.
1#
#336000
0.
0#
#338000
b1111111111111011 /
b11011 ,
1.
1#
#340000
0*
0.
0#
0'
#342000
b1111111111111100 /
b11100 ,
1.
1#
#344000
0.
0#
#346000
b1111111111111101 /
b11101 ,
1.
1#
#348000
0.
0#
#350000
b1111111111111110 /
b11110 ,
1.
1#
#352000
0.
0#
#354000
b1111111111111111 /
b11111 ,
1.
1#
#356000
0.
0#
#358000
1+
b11 0
b0 /
b100000 ,
1.
1#
#360000
0.
0#
#362000
b1 0
b1111111111110000 /
0+
11
b100001 ,
1.
1#
#364000
0.
0#
#366000
b1111111111110001 /
b100010 ,
1.
1#
#368000
0.
0#
#370000
b1111111111110010 /
b100011 ,
1.
1#
#372000
0.
0#
#374000
b1111111111110011 /
b100100 ,
1.
1#
#376000
0.
0#
#378000
b1111111111110100 /
b100101 ,
1.
1#
#380000
0.
0#
#382000
b1111111111110101 /
b100110 ,
1.
1#
#384000
0.
0#
#386000
b1111111111110110 /
b100111 ,
1.
1#
#388000
0.
0#
#390000
b1111111111110111 /
b101000 ,
1.
1#
#392000
0.
0#
#394000
b1111111111111000 /
b101001 ,
1.
1#
#396000
0.
0#
#398000
b1111111111111001 /
b101010 ,
1.
1#
#400000
0.
0#
#402000
b1111111111111010 /
b101011 ,
1.
1#
#404000
0.
0#
#406000
b1111111111111011 /
b101100 ,
1.
1#
#408000
0.
0#
#410000
b1111111111111100 /
b101101 ,
1.
1#
#412000
0.
0#
#414000
b1111111111111101 /
b101110 ,
1.
1#
#416000
0.
0#
#418000
b1111111111111110 /
b101111 ,
1.
1#
#420000
0.
0#
#422000
b1111111111111111 /
b110000 ,
1.
1#
#424000
0.
0#
#426000
1+
b11 0
b0 /
b110001 ,
1.
1#
#428000
0.
0#
#430000
b1 0
b1111111111110000 /
0+
b110010 ,
1.
1#
#432000
0.
0#
#434000
b1111111111110001 /
b110011 ,
1.
1#
#436000
0.
0#
#438000
b1111111111110010 /
b110100 ,
1.
1#
#440000
1*
0.
0#
1'
#442000
01
b1111111111110011 /
b110101 ,
1.
1#
#444000
0.
0#
#446000
b1111111111110100 /
b110110 ,
1.
1#
#448000
0.
0#
#450000
b1111111111110101 /
b110111 ,
0*
1.
1#
0'
#452000
0.
0#
#454000
b1111111111110110 /
b111000 ,
1.
1#
#456000
0.
0#
#458000
b1111111111110111 /
b111001 ,
1.
1#
#460000
0.
0#
#462000
b1111111111111000 /
b111010 ,
1.
1#
#464000
0.
0#
#466000
b1111111111111001 /
b111011 ,
1.
1#
#468000
0.
0#
#470000
b1111111111111010 /
b111100 ,
1.
1#
#472000
0.
0#
#474000
b1111111111111011 /
b111101 ,
1.
1#
#476000
0.
0#
#478000
b1111111111111100 /
b111110 ,
1.
1#
#480000
0.
0#
#482000
b1111111111111101 /
b111111 ,
1.
1#
#484000
0.
0#
#486000
b1111111111111110 /
b1000000 ,
1.
1#
#488000
0.
0#
#490000
b1111111111111111 /
b1000001 ,
1.
1#
#492000
0.
0#
#494000
1+
b11 0
b0 /
b1000010 ,
1.
1#
#496000
0.
0#
#498000
b1 0
b1111111111110000 /
0+
11
b1000011 ,
1.
1#
#500000
0.
0#
#502000
b1111111111110001 /
b1000100 ,
1.
1#
#504000
0.
0#
#506000
b1111111111110010 /
b1000101 ,
1.
1#
#508000
0.
0#
#510000
b1111111111110011 /
b1000110 ,
1.
1#
#512000
0.
0#
#514000
b1111111111110100 /
b1000111 ,
1.
1#
#516000
0.
0#
#518000
b1111111111110101 /
b1001000 ,
1.
1#
#520000
0.
0#
#522000
b1111111111110110 /
b1001001 ,
1.
1#
#524000
0.
0#
#526000
b1111111111110111 /
b1001010 ,
1.
1#
#528000
0.
0#
#530000
b1111111111111000 /
b1001011 ,
1.
1#
#532000
0.
0#
#534000
b1111111111111001 /
b1001100 ,
1.
1#
#536000
0.
0#
#538000
b1111111111111010 /
b1001101 ,
1.
1#
#540000
0.
0#
#542000
b1111111111111011 /
b1001110 ,
1.
1#
#544000
0.
0#
#546000
b1111111111111100 /
b1001111 ,
1.
1#
#548000
0.
0#
#550000
b1111111111111101 /
b1010000 ,
1.
1#
#552000
0.
0#
#554000
b1111111111111110 /
b1010001 ,
1.
1#
#556000
0.
0#
#558000
b1111111111111111 /
b1010010 ,
1.
1#
#560000
0.
0#
#562000
1+
b11 0
b0 /
b1010011 ,
1.
1#
#564000
0.
0#
#566000
b1 0
b1111111111110000 /
0+
b1010100 ,
1.
1#
#568000
0.
0#
#570000
b1111111111110001 /
b1010101 ,
1.
1#
#572000
0.
0#
#574000
b1111111111110010 /
b1010110 ,
1.
1#
#576000
0.
0#
#578000
b1111111111110011 /
b1010111 ,
1.
1#
#580000
0.
0#
#582000
b1111111111110100 /
b1011000 ,
1.
1#
#584000
0.
0#
#586000
b1111111111110101 /
b1011001 ,
1.
1#
#588000
0.
0#
#590000
b1111111111110110 /
b1011010 ,
1.
1#
#592000
0.
0#
#594000
b1111111111110111 /
b1011011 ,
1.
1#
#596000
0.
0#
#598000
b1111111111111000 /
b1011100 ,
1.
1#
#600000
0.
0#
#602000
b1111111111111001 /
b1011101 ,
1.
1#
#604000
0.
0#
#606000
b1111111111111010 /
b1011110 ,
1.
1#
#608000
0.
0#
#610000
b1111111111111011 /
b1011111 ,
1.
1#
#612000
0.
0#
#614000
b1111111111111100 /
b1100000 ,
1.
1#
#616000
0.
0#
#618000
b1111111111111101 /
b1100001 ,
1.
1#
#620000
0.
0#
#622000
b1111111111111110 /
b1100010 ,
1.
1#
#624000
0.
0#
#626000
b1111111111111111 /
b1100011 ,
1.
1#
#628000
0.
0#
#630000
1+
b11 0
b0 /
b1100100 ,
1.
1#
#632000
0.
0#
#634000
b1 0
b1111111111110000 /
0+
b1100101 ,
1.
1#
#636000
0.
0#
#638000
b1111111111110001 /
b1100110 ,
1.
1#
#640000
0.
0#
#642000
b1111111111110010 /
b1100111 ,
1.
1#
#644000
0.
0#
#646000
b1111111111110011 /
b1101000 ,
1.
1#
#648000
0.
0#
#650000
b1111111111110100 /
b1101001 ,
1.
1#
#652000
0.
0#
#654000
b1111111111110101 /
b1101010 ,
1.
1#
#656000
0.
0#
#658000
b1111111111110110 /
b1101011 ,
1.
1#
#660000
0.
0#
#662000
b1111111111110111 /
b1101100 ,
1.
1#
#664000
0.
0#
#666000
b1111111111111000 /
b1101101 ,
1.
1#
#668000
0.
0#
#670000
b1111111111111001 /
b1101110 ,
1.
1#
#672000
0.
0#
#674000
b1111111111111010 /
b1101111 ,
1.
1#
#676000
0.
0#
#678000
b1111111111111011 /
b1110000 ,
1.
1#
#680000
0.
0#
#682000
b1111111111111100 /
b1110001 ,
1.
1#
#684000
0.
0#
#686000
b1111111111111101 /
b1110010 ,
1.
1#
#688000
0.
0#
#690000
b1111111111111110 /
b1110011 ,
1.
1#
#692000
0.
0#
#694000
b1111111111111111 /
b1110100 ,
1.
1#
#696000
0.
0#
#698000
1+
b11 0
b0 /
b1110101 ,
1.
1#
#700000
0.
0#
