pacoblaze/bamse_v1/iverilog/timer/timer.v
`ifndef TIMER_V
`define TIMER_V

module timer(
	clk_in,
	rst,
	prescaler_conf,
	timer_conf,
	en,
	go,
	auto_load,
	tmr_int	
);

input clk_in;
input rst;
input [2:0] prescaler_conf;
input [15:0] timer_conf; 
input en; //enable (H)
input go; //start (H)
input auto_load; //automatic restart timer after rolloff (H)
output reg tmr_int; //interrupt (H)

reg [6:0] prescaler_out;

//Prescaler
reg prescaler_reset;

always @(posedge clk_in) begin
	if (rst) begin
		prescaler_out <= 0;		
	end else begin
		if (en) begin
			if (prescaler_reset) begin
				prescaler_out <= 0;
			end else begin
				prescaler_out <= prescaler_out + 1;
			end		
		end
	end
end

//Prescaler selector

reg selected_freq;

always @(*) begin
	case (prescaler_conf)
		3'b000: selected_freq = clk_in;
		3'b001: selected_freq = prescaler_out[0];
		3'b010: selected_freq = prescaler_out[1];
		3'b011: selected_freq = prescaler_out[2];
		3'b100: selected_freq = prescaler_out[3];
		3'b101: selected_freq = prescaler_out[4]; 
		3'b110: selected_freq = prescaler_out[5];
		3'b111: selected_freq = prescaler_out[6];
	endcase
end

//Timer
reg [15:0] timer_count;
reg [1:0] timer_state;

parameter IDLE  = 2'b00, 
		  GO =    2'b01,
		  ROLL  = 2'b11;

always @(posedge selected_freq) begin
	if (rst) begin
		timer_count <= 0;					
		tmr_int <= 0;
		timer_state <= IDLE;
		prescaler_reset <= 0;
	end else begin 
		if (en) begin
			case (timer_state)
				IDLE:	begin
							if (go) begin 
								timer_count <= timer_conf;														
								timer_state <= GO;
								prescaler_reset <= 1;
							end else begin
								tmr_int <= 0; //When go == L the interrupt is reset
							end
						end
				GO:		begin 
							prescaler_reset <= 0;
							timer_count <= timer_count + 1;
							if (timer_count == 16'hffff) begin
								timer_state <= ROLL;
							end
							
							if (go == 0) begin
								tmr_int <= 0;
								timer_state <= IDLE;
							end
						end
				ROLL: 	begin
							tmr_int <= 1;
							if (auto_load) begin
								timer_count <= timer_conf;														
								timer_state <= GO;
							end else begin
								timer_state <= IDLE;
							end
						end
				default: timer_state <= IDLE;
			endcase
		end
	
	end
end

endmodule

`endif

pacoblaze/bamse_v1/iverilog/timer/timer_tb.v
//timer_tb.v

`timescale 1ns/1ps

`include "timer.v"

module timer_tb();

reg clk_in;
reg rst;
reg [2:0] prescaler_conf;
reg [15:0] timer_conf; 
reg en; //enable (H)
reg go; //start (H)
reg auto_load; //automatic restart timer after rolloff (H)
wire tmr_int; //interrupt (H)

timer dut(
	.clk_in(clk_in),
	.rst(rst),
	.prescaler_conf(prescaler_conf),
	.timer_conf(timer_conf),
	.en(en),
	.go(go),
	.auto_load(auto_load),
	.tmr_int(tmr_int)
);

always #(2) clk_in = ~clk_in;

initial begin
	$dumpfile("dump.vcd");
	$dumpvars(1,dut);
	
	clk_in = 0;
	rst = 0;
	prescaler_conf = 0;
	timer_conf = 16'hfff0;
	en = 0;
	go = 0;
	auto_load = 0;
	
	#10 rst = 1;
	#10 rst = 0;
	#50 en = 1;
	#10 go = 1;
		
	#100 rst = 1;
	#10 rst = 0;
	#10 auto_load = 1;
	#100 go = 0;
	
	
	#(150) $finish;
end

endmodule

pacoblaze/bamse_v1/iverilog/timer/dump.vcd
$date
	Wed Oct  2 00:54:29 2019
$end
$version
	Icarus Verilog
$end
$timescale
	1ps
$end
$scope module timer_tb $end
$scope module dut $end
$var wire 1 ! auto_load $end
$var wire 1 " clk_in $end
$var wire 1 # en $end
$var wire 1 $ go $end
$var wire 3 % prescaler_conf [2:0] $end
$var wire 1 & rst $end
$var wire 16 ' timer_conf [15:0] $end
$var reg 7 ( prescaler_out [6:0] $end
$var reg 1 ) prescaler_reset $end
$var reg 1 * selected_freq $end
$var reg 16 + timer_count [15:0] $end
$var reg 2 , timer_state [1:0] $end
$var reg 1 - tmr_int $end
$upscope $end
$upscope $end
$enddefinitions $end
#0
$dumpvars
x-
bx ,
bx +
0*
x)
bx (
b1111111111110000 '
0&
b0 %
0$
0#
0"
0!
$end
#2000
1*
1"
#4000
0*
0"
#6000
1*
1"
#8000
0*
0"
#10000
0)
b0 ,
0-
b0 +
b0 (
1*
1"
1&
#12000
0*
0"
#14000
1*
1"
#16000
0*
0"
#18000
1*
1"
#20000
0*
0"
0&
#22000
1*
1"
#24000
0*
0"
#26000
1*
1"
#28000
0*
0"
#30000
1*
1"
#32000
0*
0"
#34000
1*
1"
#36000
0*
0"
#38000
1*
1"
#40000
0*
0"
#42000
1*
1"
#44000
0*
0"
#46000
1*
1"
#48000
0*
0"
#50000
1*
1"
#52000
0*
0"
#54000
1*
1"
#56000
0*
0"
#58000
1*
1"
#60000
0*
0"
#62000
1*
1"
#64000
0*
0"
#66000
1*
1"
#68000
0*
0"
#70000
b1 (
1*
1"
1#
#72000
0*
0"
#74000
b10 (
1*
1"
#76000
0*
0"
#78000
b11 (
1*
1"
#80000
0*
0"
1$
#82000
1)
b1 ,
b1111111111110000 +
b100 (
1*
1"
#84000
0*
0"
#86000
b1111111111110001 +
0)
b0 (
1*
1"
#88000
0*
0"
#90000
b1111111111110010 +
b1 (
1*
1"
#92000
0*
0"
#94000
b1111111111110011 +
b10 (
1*
1"
#96000
0*
0"
#98000
b1111111111110100 +
b11 (
1*
1"
#100000
0*
0"
#102000
b1111111111110101 +
b100 (
1*
1"
#104000
0*
0"
#106000
b1111111111110110 +
b101 (
1*
1"
#108000
0*
0"
#110000
b1111111111110111 +
b110 (
1*
1"
#112000
0*
0"
#114000
b1111111111111000 +
b111 (
1*
1"
#116000
0*
0"
#118000
b1111111111111001 +
b1000 (
1*
1"
#120000
0*
0"
#122000
b1111111111111010 +
b1001 (
1*
1"
#124000
0*
0"
#126000
b1111111111111011 +
b1010 (
1*
1"
#128000
0*
0"
#130000
b1111111111111100 +
b1011 (
1*
1"
#132000
0*
0"
#134000
b1111111111111101 +
b1100 (
1*
1"
#136000
0*
0"
#138000
b1111111111111110 +
b1101 (
1*
1"
#140000
0*
0"
#142000
b1111111111111111 +
b1110 (
1*
1"
#144000
0*
0"
#146000
b11 ,
b0 +
b1111 (
1*
1"
#148000
0*
0"
#150000
b0 ,
1-
b10000 (
1*
1"
#152000
0*
0"
#154000
1)
b1 ,
b1111111111110000 +
b10001 (
1*
1"
#156000
0*
0"
#158000
b1111111111110001 +
0)
b0 (
1*
1"
#160000
0*
0"
#162000
b1111111111110010 +
b1 (
1*
1"
#164000
0*
0"
#166000
b1111111111110011 +
b10 (
1*
1"
#168000
0*
0"
#170000
b1111111111110100 +
b11 (
1*
1"
#172000
0*
0"
#174000
b1111111111110101 +
b100 (
1*
1"
#176000
0*
0"
#178000
b1111111111110110 +
b101 (
1*
1"
#180000
0*
0"
1&
#182000
b0 ,
0-
b0 +
b0 (
1*
1"
#184000
0*
0"
#186000
1*
1"
#188000
0*
0"
#190000
1)
b1 ,
b1111111111110000 +
b1 (
1*
1"
0&
#192000
0*
0"
#194000
b1111111111110001 +
0)
b0 (
1*
1"
#196000
0*
0"
#198000
b1111111111110010 +
b1 (
1*
1"
#200000
0*
0"
1!
#202000
b1111111111110011 +
b10 (
1*
1"
#204000
0*
0"
#206000
b1111111111110100 +
b11 (
1*
1"
#208000
0*
0"
#210000
b1111111111110101 +
b100 (
1*
1"
#212000
0*
0"
#214000
b1111111111110110 +
b101 (
1*
1"
#216000
0*
0"
#218000
b1111111111110111 +
b110 (
1*
1"
#220000
0*
0"
#222000
b1111111111111000 +
b111 (
1*
1"
#224000
0*
0"
#226000
b1111111111111001 +
b1000 (
1*
1"
#228000
0*
0"
#230000
b1111111111111010 +
b1001 (
1*
1"
#232000
0*
0"
#234000
b1111111111111011 +
b1010 (
1*
1"
#236000
0*
0"
#238000
b1111111111111100 +
b1011 (
1*
1"
#240000
0*
0"
#242000
b1111111111111101 +
b1100 (
1*
1"
#244000
0*
0"
#246000
b1111111111111110 +
b1101 (
1*
1"
#248000
0*
0"
#250000
b1111111111111111 +
b1110 (
1*
1"
#252000
0*
0"
#254000
b11 ,
b0 +
b1111 (
1*
1"
#256000
0*
0"
#258000
b1 ,
b1111111111110000 +
1-
b10000 (
1*
1"
#260000
0*
0"
#262000
b1111111111110001 +
b10001 (
1*
1"
#264000
0*
0"
#266000
b1111111111110010 +
b10010 (
1*
1"
#268000
0*
0"
#270000
b1111111111110011 +
b10011 (
1*
1"
#272000
0*
0"
#274000
b1111111111110100 +
b10100 (
1*
1"
#276000
0*
0"
#278000
b1111111111110101 +
b10101 (
1*
1"
#280000
0*
0"
#282000
b1111111111110110 +
b10110 (
1*
1"
#284000
0*
0"
#286000
b1111111111110111 +
b10111 (
1*
1"
#288000
0*
0"
#290000
b1111111111111000 +
b11000 (
1*
1"
#292000
0*
0"
#294000
b1111111111111001 +
b11001 (
1*
1"
#296000
0*
0"
#298000
b1111111111111010 +
b11010 (
1*
1"
#300000
0*
0"
0$
#302000
b0 ,
0-
b1111111111111011 +
b11011 (
1*
1"
#304000
0*
0"
#306000
b11100 (
1*
1"
#308000
0*
0"
#310000
b11101 (
1*
1"
#312000
0*
0"
#314000
b11110 (
1*
1"
#316000
0*
0"
#318000
b11111 (
1*
1"
#320000
0*
0"
#322000
b100000 (
1*
1"
#324000
0*
0"
#326000
b100001 (
1*
1"
#328000
0*
0"
#330000
b100010 (
1*
1"
#332000
0*
0"
#334000
b100011 (
1*
1"
#336000
0*
0"
#338000
b100100 (
1*
1"
#340000
0*
0"
#342000
b100101 (
1*
1"
#344000
0*
0"
#346000
b100110 (
1*
1"
#348000
0*
0"
#350000
b100111 (
1*
1"
#352000
0*
0"
#354000
b101000 (
1*
1"
#356000
0*
0"
#358000
b101001 (
1*
1"
#360000
0*
0"
#362000
b101010 (
1*
1"
#364000
0*
0"
#366000
b101011 (
1*
1"
#368000
0*
0"
#370000
b101100 (
1*
1"
#372000
0*
0"
#374000
b101101 (
1*
1"
#376000
0*
0"
#378000
b101110 (
1*
1"
#380000
0*
0"
#382000
b101111 (
1*
1"
#384000
0*
0"
#386000
b110000 (
1*
1"
#388000
0*
0"
#390000
b110001 (
1*
1"
#392000
0*
0"
#394000
b110010 (
1*
1"
#396000
0*
0"
#398000
b110011 (
1*
1"
#400000
0*
0"
#402000
b110100 (
1*
1"
#404000
0*
0"
#406000
b110101 (
1*
1"
#408000
0*
0"
#410000
b110110 (
1*
1"
#412000
0*
0"
#414000
b110111 (
1*
1"
#416000
0*
0"
#418000
b111000 (
1*
1"
#420000
0*
0"
#422000
b111001 (
1*
1"
#424000
0*
0"
#426000
b111010 (
1*
1"
#428000
0*
0"
#430000
b111011 (
1*
1"
#432000
0*
0"
#434000
b111100 (
1*
1"
#436000
0*
0"
#438000
b111101 (
1*
1"
#440000
0*
0"
#442000
b111110 (
1*
1"
#444000
0*
0"
#446000
b111111 (
1*
1"
#448000
0*
0"
#450000
b1000000 (
1*
1"
