pacoblaze/bamse_v1/iverilog/gio/gio.v
/* output is a standard digital output. The output is latched by wen
 *
 */
module outport(
	address, //Port address
	value_in,	//input value
	wen, //write enable
	rst, // reset active H 
	port_out // output 
);
	parameter ADDR = 8'b0000_0000; //This parameter must be initialized during instantiation!
	
	input [7:0] address;
	input [7:0] value_in;
	input wen;
	input rst;
	output reg [7:0] port_out;

    always @(*) begin
		if (rst) begin
			port_out = 0;
		end else if (wen && (address == ADDR)) begin
			port_out = value_in;
		end 
    end
endmodule

/*  inport module is a standard digital input port. The output
 *  register "port_out" takes the value of port_in only when the address
 *  input matches ADDR. port_out must be connected to a mux controlled by
 *  ADDR.
 *  NOTE: the input does not have clock syncrhonization!
 */
module inport(
	address, //Port address
	port_in, 	
	port_out,
	ren,
	rst,
	clk
);	

	//More input ports are added here. Addresses must be initalized during instantiation! 
	parameter ADDR = 8'b0000_0000; 	
	input [7:0] address;	
	input [7:0] port_in;	
	output reg [7:0] port_out;
	input ren;
	input rst;
	input clk;
		
	always @(posedge clk) begin
		if (rst) begin
			port_out <= 0;
		end else if (ren) begin
			if (address == ADDR)
				port_out <= port_in;
		end
	end
endmodule

/* gio_ioc
 * This module configures the interrupt-on-change for a input port
 * An output port is used as configuration word to mask the bits that produce ioc
 * The inputs are syncrhonized since this port is supposed to be used
 * with external signals.
 */
 
 module inport_ioc(
	address, //Port address
	port_in, 
	port_out,
	ren,
	rst,
	clk,
	ioc_pos_conf, //rising-edge detection enable 
	ioc_neg_conf, //falling-edge detection enable	
	int_out,	//Interrupt on change 
	int_ack		//Interrupt acknowledge
);	

	parameter ADDR = 8'b0000_0000; 	
	input [7:0] address;
	input [7:0] port_in;		
	output [7:0] port_out;
	input ren;
	input rst;
	input clk;
	input [7:0] ioc_pos_conf;
	input [7:0] ioc_neg_conf;	
	output reg int_out;
	input int_ack;
	
	reg [7:0] sync_port;
	reg [7:0] c1_port;
	reg [7:0] c2_port;	
	
	reg [7:0] port_out; 
	
	wire [7:0] up_port;
	wire [7:0] down_port;
	
	//Synchronization 
	always @(posedge clk) begin
		if (rst) begin
			sync_port <= 0;
			c1_port <= 0;
			c2_port <= 0;
			port_out <= 0;
		end else begin 
			sync_port <= port_in;
			c1_port <= sync_port;
			c2_port <= c1_port;		
			if (ren) begin
				if (address == ADDR)
					port_out <= c1_port;
			end				
		end
	end
	
	assign up_port = c1_port & ~c2_port & ioc_pos_conf;
	assign down_port = ~c1_port & c2_port & ioc_pos_conf;
	
	//Interrupt
	always @(posedge clk) begin
		if (rst) begin
			int_out <= 0;
		end else begin
			if (int_ack) begin
				int_out <= 0;
			end else begin
				if (up_port | down_port) begin
					int_out <= 1;
				end
			end
		end
	end		

endmodule

module in_port_selector(
	address,
	in_port0,
	in_port1,
	//add more ports here
	out_port
);
// These parameters must be initialized during instantiation!
parameter ADDR0 = 8'h00;
parameter ADDR1 = 8'h01;
//parameter ADDR2 = 8'h02;

input [7:0] address;
input [7:0] in_port0;
input [7:0] in_port1;
output reg [7:0] out_port;

always @(*) begin
	case (address) 
		ADDR0: out_port = in_port0;
		ADDR1: out_port = in_port1;
		default: out_port = 8'h00;	
	endcase	
end

endmodule

pacoblaze/bamse_v1/iverilog/gio/inport_ioc_tb.v
//inport_ioc_tb.v
`include "gio.v"

`define PORTD_IN 8'h03
`define PORTD_IOC_POS_CONF 8'hff
`define PORTD_IOC_NEG_CONF 8'hff

module inport_ioc_tb;

reg [7:0] address;
reg [7:0] port_in;		
reg ren;
reg rst;
reg clk;
//reg [7:0] ioc_pos_conf;
//reg [7:0] ioc_neg_conf;		
reg int_ack;

wire [7:0] port_out;
wire int_out;

inport_ioc #(.ADDR(`PORTD_IN)) PortD (
	.address(address),
	.port_in(port_in),
	.port_out(port_out),
	.ren(ren),
	.rst(rst),
	.clk(clk),
	.ioc_pos_conf(`PORTD_IOC_POS_CONF),
	.ioc_neg_conf(`PORTD_IOC_NEG_CONF),
	.int_out(int_out),
	.int_ack(int_ack)
);

initial begin
	$dumpfile("dump.vcd");
	$dumpvars(0,PortD);
	
	address = 'h00;
	port_in = 'h00;
	ren = 0;
	rst = 0;
	clk = 0;
	int_ack = 0;
	
	#10 rst = 1;
	#10 rst = 0;
	#20 port_in = 8'haa;
	#30 int_ack = 1;
	#10 int_ack = 0;
	#10 address = `PORTD_IN;
	#10 ren = 1;
	#10 ren = 0;
	#20 port_in = 8'h00;
	#30 int_ack = 1;
	#10 int_ack = 0;
	#10 port_in = 8'hee;
	#10 address = 8'h10;
	#10 ren = 1;
	#10 ren = 0;
	
	#50 $finish;
	
end

always begin
	#4 clk = ~clk;
end


endmodule

pacoblaze/bamse_v1/iverilog/gio/dump.vcd
$date
	Wed Sep 18 12:23:19 2019
$end
$version
	Icarus Verilog
$end
$timescale
	1s
$end
$scope module inport_ioc_tb $end
$scope module PortD $end
$var wire 8 ! address [7:0] $end
$var wire 1 " clk $end
$var wire 8 # down_port [7:0] $end
$var wire 1 $ int_ack $end
$var wire 8 % ioc_neg_conf [7:0] $end
$var wire 8 & ioc_pos_conf [7:0] $end
$var wire 8 ' port_in [7:0] $end
$var wire 1 ( ren $end
$var wire 1 ) rst $end
$var wire 8 * up_port [7:0] $end
$var reg 8 + c1_port [7:0] $end
$var reg 8 , c2_port [7:0] $end
$var reg 1 - int_out $end
$var reg 8 . port_out [7:0] $end
$var reg 8 / sync_port [7:0] $end
$upscope $end
$upscope $end
$enddefinitions $end
#0
$dumpvars
bx /
bx .
x-
bx ,
bx +
bx *
0)
0(
b0 '
b11111111 &
b11111111 %
0$
bx #
0"
b0 !
$end
#4
b0 /
1"
#8
0"
#10
1)
#12
b0 #
b0 *
0-
b0 .
b0 ,
b0 +
1"
#16
0"
#20
1"
0)
#24
0"
#28
1"
#32
0"
#36
1"
#40
0"
b10101010 '
#44
b10101010 /
1"
#48
0"
#52
b10101010 *
b10101010 +
1"
#56
0"
#60
b0 *
1-
b10101010 ,
1"
#64
0"
#68
1"
#70
1$
#72
0"
#76
0-
1"
#80
0"
0$
#84
1"
#88
0"
#90
b11 !
#92
1"
#96
0"
#100
b10101010 .
1"
1(
#104
0"
#108
1"
#110
0(
#112
0"
#116
1"
#120
0"
#124
1"
#128
0"
#130
b0 '
#132
b0 /
1"
#136
0"
#140
b10101010 #
b0 +
1"
#144
0"
#148
b0 #
b0 ,
1-
1"
#152
0"
#156
1"
#160
0"
1$
#164
0-
1"
#168
0"
#170
0$
#172
1"
#176
0"
#180
b11101110 /
1"
b11101110 '
#184
0"
#188
b11101110 *
b11101110 +
1"
#190
b10000 !
#192
0"
#196
b0 *
b11101110 ,
1-
1"
#200
0"
1(
#204
1"
#208
0"
#210
0(
