pacoblaze/bamse_v1/iverilog/gio/bamse_inc.v
//bamse_inc.v
`ifndef BAMSE_INC
`define BAMSE_INC

// PORTA_IN is an interrupt-on-change input port
`define PORTA_IN_WIDTH 3
`define PORTA_IN 8'h01 //address input port
`define PORTA_IOC_POS_CONF 8'h02 //address rising edge conf. register
`define PORTA_IOC_NEG_CONF 8'h03 //address falling edge conf. register

// PORTB_IN is a standard digital input port (8 bits)
`define PORTB_IN_WIDTH 8
`define PORTB_IN 8'h04

// PORTC_OUT is a standard digital output port (8 bits)
`define PORTC_OUT_WIDTH 8
`define PORTC_OUT 8'h05

`endif

pacoblaze/bamse_v1/iverilog/gio/gio.v
/* output is a standard digital output. The output is latched by wen
 *
 */
module outport(
	address, //Port address
	value_in,	//input value
	wen, //write enable
	rst, // reset active H 
	port_out // output 
);
	parameter ADDR = 8'b0000_0000; //This parameter must be initialized during instantiation!
	parameter WIDTH = 8;
	
	input [7:0] address;
	input [WIDTH-1:0] value_in;
	input wen;
	input rst;
	output reg [WIDTH-1:0] port_out;

    always @(*) begin
		if (rst) begin
			port_out = 0;
		end else if (wen && (address == ADDR)) begin
			port_out = value_in;
		end 
    end
endmodule

/*  inport module is a standard digital input port. The output
 *  register "port_out" takes the value of port_in only when the address
 *  input matches ADDR. port_out must be connected to a mux controlled by
 *  ADDR.
 *  NOTE: the input does not have clock syncrhonization!
 */
module inport(
	address, //Port address
	port_in, 	
	port_out,
	ren,
	rst,
	clk
);	

	//More input ports are added here. Addresses must be initalized during instantiation! 
	parameter ADDR = 8'b0000_0000; 	
	parameter WIDTH = 8;
	
	input [7:0] address;	
	input [WIDTH-1:0] port_in;	
	output reg [WIDTH-1:0] port_out;
	input ren;
	input rst;
	input clk;
		
	always @(posedge clk) begin
		if (rst) begin
			port_out <= 0;
		end else if (ren) begin
			if (address == ADDR)
				port_out <= port_in;
		end
	end
endmodule

/* gio_ioc
 * This module configures the interrupt-on-change for a input port
 * An output port is used as configuration word to mask the bits that produce ioc
 * The inputs are syncrhonized since this port is supposed to be used
 * with external signals.
 */
 
 module inport_ioc(
	address, //Port address
	port_in, 
	port_out,
	ren,
	rst,
	clk,
	ioc_pos_conf, //rising-edge detection enable 
	ioc_neg_conf, //falling-edge detection enable	
	int_out,	//Interrupt on change 
	int_ack		//Interrupt acknowledge
);	

	parameter ADDR = 8'b0000_0000; 	
	parameter WIDTH = 3;
	
	input [7:0] address;
	input [WIDTH-1:0] port_in;		
	output [WIDTH-1:0] port_out;
	input ren;
	input rst;
	input clk;
	input [WIDTH-1:0] ioc_pos_conf;
	input [WIDTH-1:0] ioc_neg_conf;	
	output reg int_out;
	input int_ack;
	
	reg [WIDTH-1:0] sync_port;
	reg [WIDTH-1:0] c1_port;
	reg [WIDTH-1:0] c2_port;	
	
	reg [WIDTH-1:0] port_out; 
	
	wire [WIDTH-1:0] up_port;
	wire [WIDTH-1:0] down_port;
	
	//Synchronization 
	always @(posedge clk) begin
		if (rst) begin
			sync_port <= 0;
			c1_port <= 0;
			c2_port <= 0;
			port_out <= 0;
		end else begin 
			sync_port <= port_in;
			c1_port <= sync_port;
			c2_port <= c1_port;		
			if (ren) begin
				if (address == ADDR)
					port_out <= c1_port;
			end				
		end
	end
	
	assign up_port = c1_port & ~c2_port & ioc_pos_conf;
	assign down_port = ~c1_port & c2_port & ioc_neg_conf;
	
	//Interrupt
	always @(posedge clk) begin
		if (rst) begin
			int_out <= 0;
		end else begin
			if (int_ack) begin
				int_out <= 0;
			end else begin
				if (up_port | down_port) begin
					int_out <= 1;
				end
			end
		end
	end		

endmodule

//Note of in_port_selector are 7 bits, however the inputs can be of
// variable WIDTH and therefore a concat bus
// with a size 7:0 needs to be created and passed as input.
 
module in_port_selector(
	address,
	in_port0,
	in_port1,
	//add more ports here
	out_port
);

// These parameters must be initialized during instantiation!
parameter ADDR0 = 8'h00;
parameter ADDR1 = 8'h01;
//parameter ADDR2 = 8'h02;

input [7:0] address;
input [7:0] in_port0;
input [7:0] in_port1;
output reg [7:0] out_port;

always @(*) begin
	case (address) 
		ADDR0: out_port = in_port0;
		ADDR1: out_port = in_port1;
		default: out_port = 8'h00;	
	endcase	
end

endmodule

pacoblaze/bamse_v1/iverilog/gio/io_bamse.v
//io_bamse.v

`ifndef IO_BAMSE
`define BIO_BAMSE

`include "bamse_inc.v"
`include "gio.v"
 
module io_bamse(
    //Ports 
	PortA,
	PortB,
	PortC,	
	//Pacoblaze pins
	port_id,  //from port address in Pacoblaze
	port_out,  // to input port in Pacoblaze 
	port_in, // from output port in Pacoblaze
	interrupt, // to interrupt in Pacoblaze 
	interrupt_ack, // from interrupt ack Pacoblaze
	clk,
	rst,
	wen,
	ren
);

input  [`PORTA_IN_WIDTH-1:0] PortA;
input  [`PORTB_IN_WIDTH-1:0] PortB;
output [`PORTC_OUT_WIDTH-1:0] PortC;	
	//Pacoblaze pins
input [7:0]	port_id;
output [7:0] port_out;
input [7:0]	port_in;
output interrupt;
input  interrupt_ack;
input clk;
input rst;
input wen;
input ren;

/******************/
/***** PORTA ******/
/******************/

wire [`PORTA_IN_WIDTH-1:0] portA_IOC_Pos_bus;

//IOC Configuration register rising edge 
outport #(.ADDR(`PORTA_IOC_POS_CONF), .WIDTH(`PORTA_IN_WIDTH)) PortA_IOC_Pos_Conf(
	.address(port_id),
	.value_in(port_in[`PORTA_IN_WIDTH-1:0]),
	.wen(wen),
	.rst(rst),
	.port_out(portA_IOC_Pos_bus)	
);

//IOC Configuration register falling edge
wire [`PORTA_IN_WIDTH-1:0] portA_IOC_Neg_bus;

outport #(.ADDR(`PORTA_IOC_NEG_CONF), .WIDTH(`PORTA_IN_WIDTH)) PortA_IOC_Neg_Conf(
	.address(port_id),
	.value_in(port_in[`PORTA_IN_WIDTH-1:0]),
	.wen(wen),
	.rst(rst),
	.port_out(portA_IOC_Neg_bus)	
);

//Port A input
wire [`PORTA_IN_WIDTH-1:0] portA_bus;

inport_ioc #(.ADDR(`PORTA_IN), .WIDTH(`PORTA_IN_WIDTH)) Port_A (
	.address(port_id),
	.port_in(PortA),
	.port_out(portA_bus),
	.ren(ren),
	.rst(rst),
	.clk(clk),
	.ioc_pos_conf(portA_IOC_Pos_bus),
	.ioc_neg_conf(portA_IOC_Neg_bus),
	.int_out(interrupt),
	.int_ack(interrupt_ack)
);

wire [7:0] portA_bus_8;
assign portA_bus_8 = {{(8-`PORTA_IN_WIDTH){1'b0}},portA_bus};

/****************/
/**** PORTB *****/
/****************/

wire [`PORTB_IN_WIDTH-1:0] portB_bus;

inport #(.ADDR(`PORTB_IN), .WIDTH(`PORTB_IN_WIDTH)) Port_B(
	.address(port_id),
	.port_in(PortB),
	.port_out(portB_bus),
	.ren(ren),
	.rst(rst),
	.clk(clk)	
);

wire [7:0] portB_bus_8;
assign portB_bus_8 = {{(8-`PORTB_IN_WIDTH){1'b0}},portB_bus};

/****************/
/**** PORTC *****/
/****************/

outport #(.ADDR(`PORTC_OUT), .WIDTH(`PORTC_OUT_WIDTH)) Port_C(
	.address(port_id),
	.value_in(port_in[`PORTC_OUT_WIDTH-1:0]),
	.wen(wen),
	.rst(rst),
	.port_out(PortC)	
);

/****************/
/* INPUT MUX    */
/****************/

in_port_selector #(.ADDR0(`PORTA_IN), .ADDR1(`PORTB_IN))
	input_ports(
		.address(port_id),
		.in_port0(portA_bus_8),
		.in_port1(portB_bus_8),
		.out_port(port_out)
);


endmodule

`endif

pacoblaze/bamse_v1/iverilog/gio/io_bamse_tb.v
//io_bamse_tb

`include "io_bamse.v"

module io_bamse_tb();

reg  [`PORTA_IN_WIDTH-1:0] PortA;
reg  [`PORTB_IN_WIDTH-1:0] PortB;
wire [`PORTC_OUT_WIDTH-1:0] PortC;	
	//Pacoblaze pins
reg [7:0]	port_id;
wire [7:0] port_out;
reg [7:0]	port_in;
wire interrupt;
reg  interrupt_ack;
reg clk;
reg rst;
reg wen;
reg ren;

io_bamse ports(
	//Ports 
	.PortA(PortA),
	.PortB(PortB),
	.PortC(PortC),	
	//Pacoblaze pins
	.port_id(port_id),  //from port address in Pacoblaze
	.port_out(port_out),  // to input port in Pacoblaze 
	.port_in(port_in), // from output port in Pacoblaze
	.interrupt(interrupt), // to interrupt in Pacoblaze 
	.interrupt_ack(interrupt_ack), // from interrupt ack Pacoblaze
	.clk(clk),
	.rst(rst),
	.wen(wen),
	.ren(ren)
);

initial begin
	$dumpfile("dump.vcd");
	$dumpvars(0,ports);	
	
	PortA = 0;
	PortB = 0;
	port_id = 0;
	port_in = 0;
	interrupt_ack = 0;
	clk = 0;
	rst = 0;
	wen = 0; 
	ren = 0;	
	#10 rst = 1;
	#10 rst = 0;
	
	write_config_PORTA;
	interrupt_read_PORTA;
	read_PORTB;	
	write_PORTC;
	
	#100 $finish;
	
end

task write_config_PORTA;
	begin
	// Write to PORTA configuration registers
	#10 port_id = `PORTA_IOC_POS_CONF;
	#10 port_in = 3'b011;
	#10 wen = 1;
	#10 wen = 0;
	#10 port_id = `PORTA_IOC_NEG_CONF;
	#10 port_in = 3'b101;
	#10 wen = 1;
	#10 wen = 0;	
	end
endtask

task interrupt_read_PORTA;
	begin
	// Interruption and read of PORTA
	#10 PortA = 3'b001;
	#30 interrupt_ack = 1;
	#10 interrupt_ack = 0;
	#10 port_id = `PORTA_IN;
	#10 ren = 1;
	#10 ren = 0;
	#40 PortA = 0;
	#30 interrupt_ack = 1;
	#10 interrupt_ack = 0;
	
	#10 PortA = 3'b010;
	#30 interrupt_ack = 1;
	#10 interrupt_ack = 0;
	#10 port_id = `PORTA_IN;
	#10 ren = 1;
	#10 ren = 0;
	#40 PortA = 0;
	#30 interrupt_ack = 1;
	#10 interrupt_ack = 0;
	
	#10 PortA = 3'b100;
	#30 interrupt_ack = 1;
	#10 interrupt_ack = 0;
	#10 port_id = `PORTA_IN;
	#10 ren = 1;
	#10 ren = 0;
	#40 PortA = 0;
	#30 interrupt_ack = 1;
	#10 interrupt_ack = 0;
	end
endtask

task read_PORTB;
	begin
	#10 PortB = 8'hbb;
	#10 port_id = `PORTB_IN;
	#10 ren = 1;
	#10 ren = 0;
	end	
endtask

task write_PORTC;
	begin
	#10 port_id = `PORTC_OUT;
	#10 port_in = 8'hcc;
	#10 wen = 1;
	#10 wen = 0;	
	end
endtask

always begin
	#4 clk = ~clk;
end

endmodule

pacoblaze/bamse_v1/iverilog/gio/dump.vcd
$date
	Thu Sep 19 00:25:47 2019
$end
$version
	Icarus Verilog
$end
$timescale
	1s
$end
$scope module io_bamse_tb $end
$scope module ports $end
$var wire 3 ! PortA [2:0] $end
$var wire 8 " PortB [7:0] $end
$var wire 1 # clk $end
$var wire 1 $ interrupt_ack $end
$var wire 8 % port_id [7:0] $end
$var wire 8 & port_in [7:0] $end
$var wire 1 ' ren $end
$var wire 1 ( rst $end
$var wire 1 ) wen $end
$var wire 8 * port_out [7:0] $end
$var wire 8 + portB_bus_8 [7:0] $end
$var wire 8 , portB_bus [7:0] $end
$var wire 8 - portA_bus_8 [7:0] $end
$var wire 3 . portA_bus [2:0] $end
$var wire 3 / portA_IOC_Pos_bus [2:0] $end
$var wire 3 0 portA_IOC_Neg_bus [2:0] $end
$var wire 1 1 interrupt $end
$var wire 8 2 PortC [7:0] $end
$scope module PortA_IOC_Neg_Conf $end
$var wire 8 3 address [7:0] $end
$var wire 1 ( rst $end
$var wire 3 4 value_in [2:0] $end
$var wire 1 ) wen $end
$var reg 3 5 port_out [2:0] $end
$upscope $end
$scope module PortA_IOC_Pos_Conf $end
$var wire 8 6 address [7:0] $end
$var wire 1 ( rst $end
$var wire 3 7 value_in [2:0] $end
$var wire 1 ) wen $end
$var reg 3 8 port_out [2:0] $end
$upscope $end
$scope module Port_A $end
$var wire 8 9 address [7:0] $end
$var wire 1 # clk $end
$var wire 3 : down_port [2:0] $end
$var wire 1 $ int_ack $end
$var wire 3 ; ioc_neg_conf [2:0] $end
$var wire 3 < ioc_pos_conf [2:0] $end
$var wire 3 = port_in [2:0] $end
$var wire 1 ' ren $end
$var wire 1 ( rst $end
$var wire 3 > up_port [2:0] $end
$var reg 3 ? c1_port [2:0] $end
$var reg 3 @ c2_port [2:0] $end
$var reg 1 1 int_out $end
$var reg 3 A port_out [2:0] $end
$var reg 3 B sync_port [2:0] $end
$upscope $end
$scope module Port_B $end
$var wire 8 C address [7:0] $end
$var wire 1 # clk $end
$var wire 8 D port_in [7:0] $end
$var wire 1 ' ren $end
$var wire 1 ( rst $end
$var reg 8 E port_out [7:0] $end
$upscope $end
$scope module Port_C $end
$var wire 8 F address [7:0] $end
$var wire 1 ( rst $end
$var wire 8 G value_in [7:0] $end
$var wire 1 ) wen $end
$var reg 8 H port_out [7:0] $end
$upscope $end
$scope module input_ports $end
$var wire 8 I address [7:0] $end
$var wire 8 J in_port0 [7:0] $end
$var wire 8 K in_port1 [7:0] $end
$var reg 8 L out_port [7:0] $end
$upscope $end
$upscope $end
$upscope $end
$enddefinitions $end
#0
$dumpvars
b0 L
bx K
b0xxx J
b0 I
bx H
b0 G
b0 F
bx E
b0 D
b0 C
bx B
bx A
bx @
bx ?
bx >
b0 =
bx <
bx ;
bx :
b0 9
bx 8
b0 7
b0 6
bx 5
b0 4
b0 3
bx 2
x1
bx 0
bx /
bx .
b0xxx -
bx ,
bx +
b0 *
0)
0(
0'
b0 &
b0 %
0$
0#
b0 "
b0 !
$end
#4
b0 B
1#
#8
0#
#10
b0 :
b0 >
b0 0
b0 5
b0 ;
b0 /
b0 8
b0 <
b0 2
b0 H
1(
#12
b0 +
b0 K
b0 ,
b0 E
01
b0 -
b0 J
b0 .
b0 A
b0 @
b0 ?
1#
#16
0#
#20
1#
0(
#24
0#
#28
1#
#30
b10 %
b10 3
b10 6
b10 9
b10 C
b10 F
b10 I
#32
0#
#36
1#
#40
b11 7
b11 4
0#
b11 &
b11 G
#44
1#
#48
0#
#50
b11 /
b11 8
b11 <
1)
#52
1#
#56
0#
#60
1#
0)
#64
0#
#68
1#
#70
b11 %
b11 3
b11 6
b11 9
b11 C
b11 F
b11 I
#72
0#
#76
1#
#80
b101 7
b101 4
0#
b101 &
b101 G
#84
1#
#88
0#
#90
b101 0
b101 5
b101 ;
1)
#92
1#
#96
0#
#100
1#
0)
#104
0#
#108
1#
#110
b1 !
b1 =
#112
0#
#116
b1 B
1#
#120
0#
#124
b1 >
b1 ?
1#
#128
0#
#132
b0 >
b1 @
11
1#
#136
0#
#140
01
1#
1$
#144
0#
#148
1#
#150
0$
#152
0#
#156
1#
#160
0#
b1 %
b1 3
b1 6
b1 9
b1 C
b1 F
b1 I
#164
1#
#168
0#
#170
1'
#172
b1 *
b1 L
b1 -
b1 J
b1 .
b1 A
1#
#176
0#
#180
1#
0'
#184
0#
#188
1#
#192
0#
#196
1#
#200
0#
#204
1#
#208
0#
#212
1#
#216
0#
#220
b0 B
1#
b0 !
b0 =
#224
0#
#228
b1 :
b0 ?
1#
#232
0#
#236
b0 :
11
b0 @
1#
#240
0#
#244
1#
#248
0#
#250
1$
#252
01
1#
#256
0#
#260
1#
0$
#264
0#
#268
1#
#270
b10 !
b10 =
#272
0#
#276
b10 B
1#
#280
0#
#284
b10 >
b10 ?
1#
#288
0#
#292
b0 >
b10 @
11
1#
#296
0#
#300
01
1#
1$
#304
0#
#308
1#
#310
0$
#312
0#
#316
1#
#320
0#
#324
1#
#328
0#
#330
1'
#332
b10 *
b10 L
b10 -
b10 J
b10 .
b10 A
1#
#336
0#
#340
1#
0'
#344
0#
#348
1#
#352
0#
#356
1#
#360
0#
#364
1#
#368
0#
#372
1#
#376
0#
#380
b0 B
1#
b0 !
b0 =
#384
0#
#388
b0 ?
1#
#392
0#
#396
b0 @
1#
#400
0#
#404
1#
#408
0#
#410
1$
#412
1#
#416
0#
#420
1#
0$
#424
0#
#428
1#
#430
b100 !
b100 =
#432
0#
#436
b100 B
1#
#440
0#
#444
b100 ?
1#
#448
0#
#452
b100 @
1#
#456
0#
#460
1#
1$
#464
0#
#468
1#
#470
0$
#472
0#
#476
1#
#480
0#
#484
1#
#488
0#
#490
1'
#492
b100 *
b100 L
b100 -
b100 J
b100 .
b100 A
1#
#496
0#
#500
1#
0'
#504
0#
#508
1#
#512
0#
#516
1#
#520
0#
#524
1#
#528
0#
#532
1#
#536
0#
#540
b0 B
1#
b0 !
b0 =
#544
0#
#548
b100 :
b0 ?
1#
#552
0#
#556
b0 :
11
b0 @
1#
#560
0#
#564
1#
#568
0#
#570
1$
#572
01
1#
#576
0#
#580
1#
0$
#584
0#
#588
1#
#590
b10111011 "
b10111011 D
#592
0#
#596
1#
#600
b0 *
b0 L
0#
b100 %
b100 3
b100 6
b100 9
b100 C
b100 F
b100 I
#604
1#
#608
0#
#610
1'
#612
b10111011 *
b10111011 L
b10111011 +
b10111011 K
b10111011 ,
b10111011 E
1#
#616
0#
#620
1#
0'
#624
0#
#628
1#
#630
b0 *
b0 L
b101 %
b101 3
b101 6
b101 9
b101 C
b101 F
b101 I
#632
0#
#636
1#
#640
b100 7
b100 4
0#
b11001100 &
b11001100 G
#644
1#
#648
0#
#650
b11001100 2
b11001100 H
1)
#652
1#
#656
0#
#660
1#
0)
